Workbook

Sheet TABELA SPOLINE
A1: ID | B1: DESCRIÇÃO | C1: LAMPADA | D1: WATTS | E1: LUMENS | F1: ALTURA | G1: LARGURA | H1: COMPRIMENTO | I1: CABO | J1: PREÇO | K1: OBS.
A2: 84 | B2: 385/2 PLAFON SMART BRANCO | C2: 2 x E27 | D2: - | E2: - | F2: 95MM | G2: 250MM | H2: 250MM | I2: - | J2: 84.588 | L2: =VLOOKUP(A2,Formulas!A:B,2,FALSE) -> 092032
A3: 85 | B3: 385/2 PLAFON SMART CAFÉ | C3: 2 x E27 | D3: - | E3: - | F3: 95MM | G3: 250MM | H3: 250MM | I3: - | J3: 84.588 | L3: =VLOOKUP(A3,Formulas!A:B,2,FALSE) -> 092033
A4: 86 | B4: 385/2 PLAFON SMART COBRE POLIDO | C4: 2 x E27 | D4: - | E4: - | F4: 95MM | G4: 250MM | H4: 250MM | I4: - | J4: 101.5056 | L4: =VLOOKUP(A4,Formulas!A:B,2,FALSE) -> 092034
A5: 90 | B5: 385/2 PLAFON SMART PRETO | C5: 2 x E27 | D5: - | E5: - | F5: 95MM | G5: 250MM | H5: 250MM | I5: - | J5: 84.588 | L5: =VLOOKUP(A5,Formulas!A:B,2,FALSE) -> 092036
A6: 97 | B6: 385/3 PLAFON SMART BRANCO | C6: 3 x E27 | D6: - | E6: - | F6: 95MM | G6: 350MM | H6: 350MM | I6: - | J6: 139.125 | L6: =VLOOKUP(A6,Formulas!A:B,2,FALSE) -> 092040
A7: 98 | B7: 385/3 PLAFON SMART CAFÉ | C7: 3 x E27 | D7: - | E7: - | F7: 95MM | G7: 350MM | H7: 350MM | I7: - | J7: 139.125 | L7: =VLOOKUP(A7,Formulas!A:B,2,FALSE) -> 092041
A8: 99 | B8: 385/3 PLAFON SMART COBRE POLIDO | C8: 3 x E27 | D8: - | E8: - | F8: 95MM | G8: 350MM | H8: 350MM | I8: - | J8: 166.95 | L8: =VLOOKUP(A8,Formulas!A:B,2,FALSE) -> 092042
A9: 103 | B9: 385/3 PLAFON SMART PRETO | C9: 3 x E27 | D9: - | E9: - | F9: 95MM | G9: 350MM | H9: 350MM | I9: - | J9: 139.125 | L9: =VLOOKUP(A9,Formulas!A:B,2,FALSE) -> 092044
A10: 110 | B10: 385/5 PLAFON SMART BRANCO | C10: 5 x E27 | D10: - | E10: - | F10: 95MM | G10: 550MM | H10: 550MM | I10: - | J10: 267.12 | L10: =VLOOKUP(A10,Formulas!A:B,2,FALSE) -> 092048
A11: 111 | B11: 385/5 PLAFON SMART CAFÉ | C11: 5 x E27 | D11: - | E11: - | F11: 95MM | G11: 550MM | H11: 550MM | I11: - | J11: 267.12 | L11: =VLOOKUP(A11,Formulas!A:B,2,FALSE) -> 092049
A12: 112 | B12: 385/5 PLAFON SMART COBRE POLIDO | C12: 5 x E27 | D12: - | E12: - | F12: 95MM | G12: 550MM | H12: 550MM | I12: - | J12: 320.544 | L12: =VLOOKUP(A12,Formulas!A:B,2,FALSE) -> 092050
A13: 116 | B13: 385/5 PLAFON SMART PRETO | C13: 5 x E27 | D13: - | E13: - | F13: 95MM | G13: 550MM | H13: 550MM | I13: - | J13: 267.12 | L13: =VLOOKUP(A13,Formulas!A:B,2,FALSE) -> 092052
... A61: 871 | B61: 733/6 PENDENTE CENTURY PRETO | C61: 6 X E27 | D61: - | E61: - | F61: 360MM | G61: 150MM | H61: 1200MM | I61: 1500MM | J61: 578.76 | L61: =VLOOKUP(A61,Formulas!A:B,2,FALSE) -> 092298
A62: 873 | B62: 735/25 PLAFON NEW SMART BRANCO3000K | C62: LED BIVOLT | D62: 18WATTS | E62: 1350 | F62: 50MM | G62: 250MM | H62: 250MM | I62: - | J62: 131.334 | L62: =VLOOKUP(A62,Formulas!A:B,2,FALSE) -> 092056
A63: 879 | B63: 735/25 PLAFON NEW SMART PRETO3000K | C63: LED BIVOLT | D63: 18WATTS | E63: 1350 | F63: 50MM | G63: 250MM | H63: 250MM | I63: - | J63: 131.334 | L63: =VLOOKUP(A63,Formulas!A:B,2,FALSE) -> 092058
A64: 882 | B64: 735/35 PLAFON NEW SMART BRANCO3000K | C64: LED BIVOLT | D64: 36WATTS | E64: 2700 | F64: 50MM | G64: 350MM | H64: 350MM | I64: - | J64: 171.402 | L64: =VLOOKUP(A64,Formulas!A:B,2,FALSE) -> 092066
A65: 891 | B65: 735/35 PLAFON NEW SMART PRETO3000K | C65: LED BIVOLT | D65: 36WATTS | E65: 2700 | F65: 50MM | G65: 350MM | H65: 350MM | I65: - | J65: 171.402 | L65: =VLOOKUP(A65,Formulas!A:B,2,FALSE) -> 092069
A66: 894 | B66: 735/50 PLAFON NEW SMART BRANCO3000K | C66: LED BIVOLT | D66: 50WATTS | E66: 3750 | F66: 50MM | G66: 500MM | H66: 500MM | I66: - | J66: 389.55 | L66: =VLOOKUP(A66,Formulas!A:B,2,FALSE) -> 092076
A67: 901 | B67: 735/50 PLAFON NEW SMART PRETO3000K | C67: LED BIVOLT | D67: 50WATTS | E67: 3750 | F67: 50MM | G67: 500MM | H67: 500MM | I67: - | J67: 389.55 | L67: =VLOOKUP(A67,Formulas!A:B,2,FALSE) -> 092078
A68: 965 | B68: 757/1 ARANDELA DROP BRANCO | C68: 1 X G9 | D68: - | E68: - | F68: 220MM | G68: 120MM | H68: 160MM | I68: - | J68: 107.961 | L68: =VLOOKUP(A68,Formulas!A:B,2,FALSE) -> 092691
A69: 968 | B69: 757/1 ARANDELA DROP DOURADO ONO | C69: 1 X G9 | D69: - | E69: - | F69: 220MM | G69: 120MM | H69: 160MM | I69: - | J69: 107.961 | L69: =VLOOKUP(A69,Formulas!A:B,2,FALSE) -> 092694
A70: 969 | B70: 757/1 ARANDELA DROP PRETO | C70: 1 X G9 | D70: - | E70: - | F70: 220MM | G70: 120MM | H70: 160MM | I70: - | J70: 107.961 | L70: =VLOOKUP(A70,Formulas!A:B,2,FALSE) -> 092695
A71: 971 | B71: 757/1 ARANDELA DROP DOURADO POLIDO | C71: 1 X G9 | D71: - | E71: - | F71: 220MM | G71: 120MM | H71: 160MM | I71: - | J71: 129.5532 | L71: =VLOOKUP(A71,Formulas!A:B,2,FALSE) -> 092696
A72: 984 | B72: 765/1 LUMINARIA DE MESA DROP BRANCO | C72: 1 X G9 | D72: - | E72: - | F72: 300MM | G72: 130MM | H72: 170MM | I72: - | J72: 144.69 | L72: =VLOOKUP(A72,Formulas!A:B,2,FALSE) -> 092901
A73: 985 | B73: 765/1 LUMINARIA DE MESA DROP COBRE POLIDO | C73: 1 X G9 | D73: - | E73: - | F73: 300MM | G73: 130MM | H73: 170MM | I73: - | J73: 173.628 | L73: =VLOOKUP(A73,Formulas!A:B,2,FALSE) -> 092902
A74: 986 | B74: 765/1 LUMINARIA DE MESA DROP DOURADO ONO | C74: 1 X G9 | D74: - | E74: - | F74: 300MM | G74: 130MM | H74: 170MM | I74: - | J74: 144.69 | L74: =VLOOKUP(A74,Formulas!A:B,2,FALSE) -> 092903
A75: 987 | B75: 765/1 LUMINARIA DE MESA DROP DOURADO POLIDO | C75: 1 X G9 | D75: - | E75: - | F75: 300MM | G75: 130MM | H75: 170MM | I75: - | J75: 173.628 | L75: =VLOOKUP(A75,Formulas!A:B,2,FALSE) -> 092904
A76: 988 | B76: 765/1 LUMINARIA DE MESA DROP PRETO | C76: 1 X G9 | D76: - | E76: - | F76: 300MM | G76: 130MM | H76: 170MM | I76: - | J76: 144.69 | L76: =VLOOKUP(A76,Formulas!A:B,2,FALSE) -> 092905
A77: 997 | B77: 777/1 ARANDELA PENDULO BRANCO VIDRO LEITOSO | C77: 1 X G9 | D77: - | E77: - | F77: 450MM | G77: 120MM | H77: 180MM | I77: - | J77: 148.029 | L77: =VLOOKUP(A77,Formulas!A:B,2,FALSE) -> 092705
A78: 1001 | B78: 777/1 ARANDELA PENDULO DOURADO ONO VIDRO LEITOSO | C78: 1 X G9 | D78: - | E78: - | F78: 450MM | G78: 120MM | H78: 180MM | I78: - | J78: 148.029 | L78: =VLOOKUP(A78,Formulas!A:B,2,FALSE) -> 092708
A79: 1002 | B79: 777/1 ARANDELA PENDULO DOURADO POLIDO VIDRO LEITOSO | C79: 1 X G9 | D79: - | E79: - | F79: 450MM | G79: 120MM | H79: 180MM | I79: - | J79: 177.6348 | L79: =VLOOKUP(A79,Formulas!A:B,2,FALSE) -> 092709
... A160: 1323 | B160: 808/5 PENDENTE GRAU PRETO / DOURADO POLIDO | C160: 4 X MR11 - 1 X G9 | D160: - | E160: - | F160: 140MM | G160: 120MM | H160: 1400MM | I160: 1200MM | J160: 686.721 | L160: =VLOOKUP(A160,Formulas!A:B,2,FALSE) -> #N/A
A161: 1332 | B161: 810/120 PENDENTE HALL BRANCO3000K | C161: LED BIVOLT | D161: 38WATTS | E161: 2850 | F161: 40MM | G161: 50MM | H161: 1200MM | I161: 1500MM | J161: 366.177 | L161: =VLOOKUP(A161,Formulas!A:B,2,FALSE) -> 092561
A162: 1333 | B162: 810/120 PENDENTE HALL PRETO3000K | C162: LED BIVOLT | D162: 38WATTS | E162: 2850 | F162: 40MM | G162: 50MM | H162: 1200MM | I162: 1500MM | J162: 366.177 | L162: =VLOOKUP(A162,Formulas!A:B,2,FALSE) -> 092562
A163: 1334 | B163: 810/120 PENDENTE HALL PRETO4000K | C163: LED BIVOLT | D163: 38WATTS | E163: 2850 | F163: 40MM | G163: 50MM | H163: 1200MM | I163: 1500MM | J163: 366.177 | L163: =VLOOKUP(A163,Formulas!A:B,2,FALSE) -> 092566
A164: 1340 | B164: 811/120 PENDENTE OFFICE BRANCO 3000K | C164: LED BIVOLT | D164: 18WATTS | E164: 1350 | F164: 40MM | G164: 50MM | H164: 1200mm | I164: 1500MM | J164: 263.781 | L164: =VLOOKUP(A164,Formulas!A:B,2,FALSE) -> 092577
A165: 1341 | B165: 811/120 PENDENTE OFFICE BRANCO 4000K | C165: LED BIVOLT | D165: 18WATTS | E165: 1350 | F165: 40MM | G165: 50MM | H165: 1200MM | I165: 1500MM | J165: 263.781 | L165: =VLOOKUP(A165,Formulas!A:B,2,FALSE) -> 092585
A166: 1343 | B166: 811/120 PENDENTE OFFICE BRANCO / DOURADO ESCOVADO 4000K | C166: LED BIVOLT | D166: 18WATTS | E166: 1350 | F166: 40MM | G166: 50MM | H166: 1200MM | I166: 1500MM | J166: 263.781 | L166: =VLOOKUP(A166,Formulas!A:B,2,FALSE) -> 092587
A167: 1344 | B167: 811/120 PENDENTE OFFICE PRETO 3000K | C167: LED BIVOLT | D167: 18WATTS | E167: 1350 | F167: 40MM | G167: 50MM | H167: 1200MM | I167: 1500MM | J167: 263.781 | L167: =VLOOKUP(A167,Formulas!A:B,2,FALSE) -> 092578
A168: 1345 | B168: 811/120 PENDENTE OFFICE PRETO 4000K | C168: LED BIVOLT | D168: 18WATTS | E168: 1350 | F168: 40MM | G168: 50MM | H168: 1200MM | I168: 1500MM | J168: 263.781 | L168: =VLOOKUP(A168,Formulas!A:B,2,FALSE) -> 092588
A169: 1347 | B169: 811/120 PENDENTE OFFICE PRETO / DOURADO ESCOVADO 4000K | C169: LED BIVOLT | D169: 18WATTS | E169: 1350 | F169: 40MM | G169: 50MM | H169: 1200MM | I169: 1500MM | J169: 263.781 | L169: =VLOOKUP(A169,Formulas!A:B,2,FALSE) -> 092590
A170: 1348 | B170: 812/120 PLAFON KIT PRETO3000K | C170: LED BIVOLT | D170: 38WATTS | E170: 2850 | F170: 80MM | G170: 120MM | H170: 1660MM | I170: - | J170: 363.951 | L170: =VLOOKUP(A170,Formulas!A:B,2,FALSE) -> #N/A
A171: 1349 | B171: 812/60 PLAFON KIT BRANCO3000K | C171: LED BIVOLT | D171: 18WATTS | E171: 1350 | F171: 80MM | G171: 120MM | H171: 750MM | I171: - | J171: 230.391 | L171: =VLOOKUP(A171,Formulas!A:B,2,FALSE) -> 092086
A172: 1350 | B172: 812/60 PLAFON KIT DOURADO ONO3000K | C172: LED BIVOLT | D172: 18WATTS | E172: 1350 | F172: 80MM | G172: 120MM | H172: 750MM | I172: - | J172: 230.391 | L172: =VLOOKUP(A172,Formulas!A:B,2,FALSE) -> 092087
... A176: 1365 | B176: 814/120 PENDENTE ROAD PRETO4000K | C176: LED BIVOLT | D176: 38WATTS | E176: 2850 | F176: 40MM | G176: 50MM | H176: 1200MM | I176: 1500MM | J176: 366.177 | L176: =VLOOKUP(A176,Formulas!A:B,2,FALSE) -> 092597
A177: 1370 | B177: 815/1 ARANDELA TROMP DOURADO ONO VIDRO LEITOSO | C177: 1 X E27 | D177: - | E177: - | F177: 780MM | G177: 150MM | H177: 300MM | I177: - | J177: 222.6 | L177: =VLOOKUP(A177,Formulas!A:B,2,FALSE) -> 092792
A178: 1372 | B178: 815/1 ARANDELA TROMP PRETO VIDRO LEITOSO | C178: 1 X E27 | D178: - | E178: - | F178: 780MM | G178: 150MM | H178: 300MM | I178: - | J178: 222.6 | L178: =VLOOKUP(A178,Formulas!A:B,2,FALSE) -> 092794
A179: 1387 | B179: 817/1 ARANDELA TORCH DOURADO POLIDO CUPULA BRANCA | C179: 1 X E27 | D179: - | E179: - | F179: 500MM | G179: 90MM | H179: 140MM | I179: - | J179: 129.5532 | L179: =VLOOKUP(A179,Formulas!A:B,2,FALSE) -> #N/A
A180: 1388 | B180: 817/1 ARANDELA TORCH PRETO CUPULA BRANCA | C180: 1 X E27 | D180: - | E180: - | F180: 500MM | G180: 90MM | H180: 140MM | I180: - | J180: 110.187 | L180: =VLOOKUP(A180,Formulas!A:B,2,FALSE) -> 092797
A181: 1390 | B181: 817/1 ARANDELA TORCH PRETO / DOURADO ESCOVADO CUPULA PRETA | C181: 1 X E27 | D181: - | E181: - | F181: 500MM | G181: 90MM | H181: 140MM | I181: - | J181: 110.187 | L181: =VLOOKUP(A181,Formulas!A:B,2,FALSE) -> 092798
A182: 1391 | B182: 817/1 ARANDELA TORCH PRETO / DOURADO ONO CUPULA CRU | C182: 1 X E27 | D182: - | E182: - | F182: 500MM | G182: 90MM | H182: 140MM | I182: - | J182: 110.187 | L182: =VLOOKUP(A182,Formulas!A:B,2,FALSE) -> 092799
A183: 1398 | B183: 820/1 ARANDELA GOTA BRANCO VIDRO LEITOSO | C183: 1 X G9 | D183: - | E183: - | F183: 430MM | G183: 170MM | H183: 160MM | I183: - | J183: 134.673 | L183: =VLOOKUP(A183,Formulas!A:B,2,FALSE) -> 092807
A184: 1399 | B184: 820/1 ARANDELA GOTA COBRE ONO VIDRO LEITOSO | C184: 1 X G9 | D184: - | E184: - | F184: 430MM | G184: 170MM | H184: 160MM | I184: - | J184: 134.673 | L184: =VLOOKUP(A184,Formulas!A:B,2,FALSE) -> 092808
A185: 1400 | B185: 820/1 ARANDELA GOTA COBRE POLIDO VIDRO LEITOSO | C185: 1 X G9 | D185: - | E185: - | F185: 430MM | G185: 170MM | H185: 160MM | I185: - | J185: 161.6076 | L185: =VLOOKUP(A185,Formulas!A:B,2,FALSE) -> 092809
A186: 1401 | B186: 820/1 ARANDELA GOTA DOURADO ONO VIDRO LEITOSO | C186: 1 X G9 | D186: - | E186: - | F186: 430MM | G186: 170MM | H186: 160MM | I186: - | J186: 134.673 | L186: =VLOOKUP(A186,Formulas!A:B,2,FALSE) -> 092810
A187: 1402 | B187: 820/1 ARANDELA GOTA DOURADO POLIDO VIDRO LEITOSO | C187: 1 X G9 | D187: - | E187: - | F187: 430MM | G187: 170MM | H187: 160MM | I187: - | J187: 161.6076 | L187: =VLOOKUP(A187,Formulas!A:B,2,FALSE) -> 092811
A188: 1406 | B188: 820/1 ARANDELA GOTA PRETO VIDRO LEITOSO | C188: 1 X G9 | D188: - | E188: - | F188: 430MM | G188: 170MM | H188: 160MM | I188: - | J188: 134.673 | L188: =VLOOKUP(A188,Formulas!A:B,2,FALSE) -> 092813
... A193: 1415 | B193: 821/1 ARANDELA MADRI PRETO/DOURADO ESCOVADO | C193: 1 X E27 | D193: - | E193: - | F193: 270MM | G193: 160MM | H193: 200MM | I193: - | J193: 150.255 | L193: =VLOOKUP(A193,Formulas!A:B,2,FALSE) -> 092823
A194: 1430 | B194: 823/60 ARANDELA STYLE DOURADO ONO3000K | C194: LED BIVOLT | D194: 13WATTS | E194: 975 | F194: 600MM | G194: 20MM | H194: 25MM | I194: - | J194: 143.577 | L194: =VLOOKUP(A194,Formulas!A:B,2,FALSE) -> 092861
A195: 1431 | B195: 823/60 ARANDELA STYLE PRETO3000K | C195: LED BIVOLT | D195: 13WATTS | E195: 975 | F195: 600MM | G195: 20MM | H195: 25MM | I195: - | J195: 143.577 | L195: =VLOOKUP(A195,Formulas!A:B,2,FALSE) -> 092862
A196: 1433 | B196: 824/30 PLAFON CASE PRETO3000K | C196: LED BIVOLT | D196: 22WATTS | E196: 1650 | F196: 80MM | G196: 300MM | H196: 300MM | I196: - | J196: 238.182 | L196: =VLOOKUP(A196,Formulas!A:B,2,FALSE) -> 092102
A197: 1434 | B197: 824/30 PLAFON CASE BRANCO3000K | C197: LED BIVOLT | D197: 22WATTS | E197: 1650 | F197: 80MM | G197: 300MM | H197: 300MM | I197: - | J197: 238.182 | L197: =VLOOKUP(A197,Formulas!A:B,2,FALSE) -> 092103
A198: 1435 | B198: 824/30 PLAFON CASE PRETO 4000K | C198: LED BIVOLT | D198: 22WATTS | E198: 1650 | F198: 80MM | G198: 300MM | H198: 300MM | I198: - | J198: 238.182 | L198: =VLOOKUP(A198,Formulas!A:B,2,FALSE) -> 092107
A199: 1437 | B199: 824/30/30 PLAFON CASE BRANCO 4000K | C199: LED BIVOLT | D199: 40WATTS | E199: 3000 | F199: 80MM | G199: 450MM | H199: 450MM | I199: - | J199: 400.68 | L199: =VLOOKUP(A199,Formulas!A:B,2,FALSE) -> 092114
A200: 1438 | B200: 824/30/30 PLAFON CASE DOURADO ONO3000K | C200: LED BIVOLT | D200: 40WATTS | E200: 3000 | F200: 80MM | G200: 450MM | H200: 450MM | I200: - | J200: 400.68 | L200: =VLOOKUP(A200,Formulas!A:B,2,FALSE) -> 092110
A201: 1439 | B201: 824/30/30 PLAFON CASE PRETO3000K | C201: LED BIVOLT | D201: 40WATTS | E201: 3000 | F201: 80MM | G201: 450MM | H201: 450MM | I201: - | J201: 400.68 | L201: =VLOOKUP(A201,Formulas!A:B,2,FALSE) -> 092111
A202: 1440 | B202: 824/30/30 PLAFON CASE PRETO 4000K | C202: LED BIVOLT | D202: 40WATTS | E202: 3000 | F202: 80MM | G202: 450MM | H202: 450MM | I202: - | J202: 400.68 | L202: =VLOOKUP(A202,Formulas!A:B,2,FALSE) -> 092115
A203: 1441 | B203: 824/30/40 PLAFON CASE PRETO3000K | C203: LED BIVOLT | D203: 45WATTS | E203: 3375 | F203: 80MM | G203: 540MM | H203: 540MM | I203: - | J203: 463.008 | L203: =VLOOKUP(A203,Formulas!A:B,2,FALSE) -> 092118
A204: 1443 | B204: 824/30/40 PLAFON CASE BRANCO3000K | C204: LED BIVOLT | D204: 45WATTS | E204: 3375 | F204: 80MM | G204: 540MM | H204: 540MM | I204: - | J204: 463.008 | L204: =VLOOKUP(A204,Formulas!A:B,2,FALSE) -> 092119
A205: 1444 | B205: 824/30/40 PLAFON CASE BRANCO 4000K | C205: LED BIVOLT | D205: 45WATTS | E205: 3375 | F205: 80MM | G205: 450MM | H205: 450MM | I205: - | J205: 463.008 | L205: =VLOOKUP(A205,Formulas!A:B,2,FALSE) -> 092123
... A222: 1482 | B222: 832/1 PENDENTE SHINE PRETO 3000K | C222: LED BIVOLT | D222: 2WATTS | E222: 112 | F222: 380MM | G222: 50MM | H222: 50MM | I222: 1500MM | J222: 178.08 | L222: =VLOOKUP(A222,Formulas!A:B,2,FALSE) -> 092658
A223: 1495 | B223: 835/1 ARANDELA DOME PRETO / DOURADO ESCOVADO | C223: 1 XG9 | D223: - | E223: - | F223: 450MM | G223: 190MM | H223: 1150MM | I223: - | J223: 200.34 | L223: =VLOOKUP(A223,Formulas!A:B,2,FALSE) -> 092868
A224: 1496 | B224: 835/1 ARANDELA DOME BRANCO | C224: 1 XG9 | D224: - | E224: - | F224: 450MM | G224: 190MM | H224: 1150MM | I224: - | J224: 200.34 | L224: =VLOOKUP(A224,Formulas!A:B,2,FALSE) -> 092869
A225: 1501 | B225: 835/1 ARANDELA DOME DOURADO POLIDO | C225: 1 XG9 | D225: - | E225: - | F225: 450MM | G225: 190MM | H225: 1150MM | I225: - | J225: 240.408 | L225: =VLOOKUP(A225,Formulas!A:B,2,FALSE) -> 092873
A226: 1502 | B226: 835/1 ARANDELA DOME PRETO | C226: 1 XG9 | D226: - | E226: - | F226: 450MM | G226: 190MM | H226: 1150MM | I226: - | J226: 200.34 | L226: =VLOOKUP(A226,Formulas!A:B,2,FALSE) -> 092874
A227: 1503 | B227: 835/1 ARANDELA DOME PRETO / DOURADO ONO | C227: 1 XG9 | D227: - | E227: - | F227: 450MM | G227: 190MM | H227: 1150MM | I227: - | J227: 200.34 | L227: =VLOOKUP(A227,Formulas!A:B,2,FALSE) -> 092875
A228: 1504 | B228: 835/1 ARANDELA DOME PRETO / DOURADO POLIDO | C228: 1 XG9 | D228: - | E228: - | F228: 450MM | G228: 190MM | H228: 1150MM | I228: - | J228: 200.34 | L228: =VLOOKUP(A228,Formulas!A:B,2,FALSE) -> 092876
A229: 1521 | B229: 837/1 COLUNA MADRI DOURADO LIXADO | C229: 1 X E27 | D229: - | E229: - | F229: 1550MM | G229: 230MM | H229: 230MM | I229: - | J229: 349.9272 | L229: =VLOOKUP(A229,Formulas!A:B,2,FALSE) -> #N/A
A230: 1522 | B230: 837/1 COLUNA MADRI BRANCO | C230: 1 X E27 | D230: - | E230: - | F230: 1550MM | G230: 230MM | H230: 230MM | I230: - | J230: 291.606 | L230: =VLOOKUP(A230,Formulas!A:B,2,FALSE) -> 092952
A231: 1525 | B231: 837/1 COLUNA MADRI PRETO | C231: 1 X E27 | D231: - | E231: - | F231: 1550MM | G231: 230MM | H231: 230MM | I231: - | J231: 291.606 | L231: =VLOOKUP(A231,Formulas!A:B,2,FALSE) -> 092955
A232: 1530 | B232: 837/1 COLUNA MADRI PRETO/DOURADO ESCOVADO | C232: 1 X E27 | D232: - | E232: - | F232: 1550MM | G232: 230MM | H232: 230MM | I232: - | J232: 291.606 | L232: =VLOOKUP(A232,Formulas!A:B,2,FALSE) -> 092960
A233: 1847 | B233: 823/60 ARANDELA STYLE BRANCO 3000K | C233: LED BIVOLT | D233: 13WATTS | E233: 975 | F233: 600MM | G233: 20MM | H233: 25MM | I233: - | J233: 143.577 | L233: =VLOOKUP(A233,Formulas!A:B,2,FALSE) -> 092863
A234: 1848 | B234: 810/120 PENDENTE HALL DOURADO ONO 3000K | C234: LED BIVOLT | D234: 38WATTS | E234: 2850 | F234: 40MM | G234: 50MM | H234: 1200MM | I234: 1500MM | J234: 366.177 | L234: =VLOOKUP(A234,Formulas!A:B,2,FALSE) -> 092563
A235: 1862 | B235: 837/1 COLUNA MADRI DOURADO ONO | C235: 1 X E27 | D235: - | E235: - | F235: 1550MM | G235: 230MM | H235: 230MM | I235: - | J235: 291.606 | L235: =VLOOKUP(A235,Formulas!A:B,2,FALSE) -> 092958
A236: 1870 | B236: 811/120 PENDENTE OFFICE PRETO / ANEL MADEIRA 4000 | C236: LED BIVOLT | D236: 18WATTS | E236: 1350 | F236: 40MM | G236: 50MM | H236: 1200MM | I236: 1500MM | J236: 263.781 | L236: =VLOOKUP(A236,Formulas!A:B,2,FALSE) -> 092591
A237: 1875 | B237: 812/120 PLAFON KIT DOURADO ONO 3000K | C237: LED BIVOLT | D237: 38WATTS | E237: 2850 | F237: 80MM | G237: 120MM | H237: 1660MM | I237: - | J237: 363.951 | L237: =VLOOKUP(A237,Formulas!A:B,2,FALSE) -> 092095
A238: 1880 | B238: 827/30-30 PENDENTE CASE PRETO 4000K | C238: LED BIVOLT | D238: 40WATTS | E238: 3000 | F238: 80MM | G238: 450MM | H238: 450MM | I238: 1500MM | J238: 338.352 | L238: =VLOOKUP(A238,Formulas!A:B,2,FALSE) -> 092623
A239: 1892 | B239: 825/30 PLAFON MAZE DOURADO ONO 3000 K | C239: LED BIVOLT | D239: 22WATTS | E239: 1650 | F239: 80MM | G239: 530MM | H239: 530MM | I239: - | J239: 271.572 | L239: =VLOOKUP(A239,Formulas!A:B,2,FALSE) -> 092127
A240: 1900 | B240: 812/120 PLAFON KIT PRETO 4000K | C240: LED BIVOLT | D240: 38WATTS | E240: 2850 | F240: 80MM | G240: 120MM | H240: 1660MM | I240: - | J240: 363.951 | L240: =VLOOKUP(A240,Formulas!A:B,2,FALSE) -> 092098
A241: 1901 | B241: 812/60 PLAFON KIT BRANCO 4000K | C241: LED BIVOLT | D241: 18WATTS | E241: 1350 | F241: 80MM | G241: 120MM | H241: 750MM | I241: - | J241: 230.391 | L241: =VLOOKUP(A241,Formulas!A:B,2,FALSE) -> 092090
A242: 1937 | B242: 811/120 PENDENTE OFFICE BRANCO / ANEL MADEIRA 3000K | C242: LED BIVOLT | D242: 18WATTS | E242: 1350 | F242: 40MM | G242: 50MM | H242: 1200MM | I242: 1500MM | J242: 263.781 | L242: =VLOOKUP(A242,Formulas!A:B,2,FALSE) -> 092579
A243: 1942 | B243: 499/1 PENDENTE VERSSAT DOURADO ONO | C243: 1 X G9 | D243: - | E243: - | F243: 500MM | G243: 25MM | H243: 25MM | I243: 1500MM | J243: 76.797 | L243: =VLOOKUP(A243,Formulas!A:B,2,FALSE) -> 092174
A244: 1945 | B244: 817/1 ARANDELA TORCH PRETO / DOURADO POLIDO CUPULA CRU | C244: 1 X E27 | D244: - | E244: - | F244: 500MM | G244: 90MM | H244: 140MM | I244: - | J244: 110.187 | L244: =VLOOKUP(A244,Formulas!A:B,2,FALSE) -> 092800
A245: 1951 | B245: 817/1 ARANDELA TORCH BRANCO CUPULA BRANCA | C245: 1 X E27 | D245: - | E245: - | F245: 500MM | G245: 90MM | H245: 140MM | I245: - | J245: 110.187 | L245: =VLOOKUP(A245,Formulas!A:B,2,FALSE) -> 092801
A246: 1990 | B246: 647/1 COLUNA DENVER DOURADO ONO / BRANCO | C246: 1 X E27 | D246: - | E246: - | F246: 1600MM | G246: 210MM | H246: 380MM | I246: - | J246: 173.628 | L246: =VLOOKUP(A246,Formulas!A:B,2,FALSE) -> #N/A
A247: 2014 | B247: 646/1 COLUNA SQUARE PRETO / BRANCO | C247: 1 X E27 | D247: - | E247: - | F247: 1580MM | G247: 210MM | H247: 210MM | I247: - | J247: 195.888 | L247: =VLOOKUP(A247,Formulas!A:B,2,FALSE) -> 092932
A248: 2019 | B248: 814/120 PENDENTE ROAD BRANCO 3000K | C248: LED BIVOLT | D248: 38WATTS | E248: 2850 | F248: 40MM | G248: 50MM | H248: 1200MM | I248: 1500MM | J248: 366.177 | L248: =VLOOKUP(A248,Formulas!A:B,2,FALSE) -> 092595
A249: 2022 | B249: 786/1 PENDENTE DELTA DOURADO POLIDO VIDRO LEITOSO | C249: 1 XG9 | D249: - | E249: - | F249: 450MM | G249: 120MM | H249: 150MM | I249: 1500MM | J249: 192.3264 | L249: =VLOOKUP(A249,Formulas!A:B,2,FALSE) -> 092402
A250: 2025 | B250: 811/120 PENDENTE OFFICE PRETO / DOURADO ESCOVADO 3000K | C250: LED BIVOLT | D250: 18WATTS | E250: 1350 | F250: 40MM | G250: 50MM | H250: 1200MM | I250: 1500MM | J250: 263.781 | L250: =VLOOKUP(A250,Formulas!A:B,2,FALSE) -> 092580
...

Sheet Formulas
A1: # Referência | B1: SKU | J1: # Referência | L1: Nome | M1: Id do Fabricante | N1: Fabricante | O1: Preço | P1: Preço Mínimo
A2: 44 | B2: 177938 | C2: =VLOOKUP(A2,'TABELA SPOLINE'!A:J,10,FALSE) -> #N/A | J2: 44 | K2: =TRIM(A2) -> 44 | L2: SPOT FLEX PTO TRILHO 2 x E27 300MM | M2: 7629 | N2: Spot Line Industria E Comercio | O2: 519,75 | P2: 311,97
A3: 84 | B3: 092032 | C3: =VLOOKUP(A3,'TABELA SPOLINE'!A:J,10,FALSE) -> 84.588 | D3: =C3*0.1+C3 -> 93.0468 | E3: =ROUNDUP(D3,2) -> 93.05 | F3: =E3*0.0975+E3 -> 102.12238 | G3: =ROUNDUP(F3,2) -> 102.13 | H3: 385 | I3: 2 | J3: 84-385-2 | K3: =TRIM(A3) -> 84 | L3: SPOT FLEX PTO / COBRE POL TRILHO 2 x E27 300MM | M3: 7629 | N3: Spot Line Industria E Comercio | O3: 353,45 | P3: 212,15
A4: 85 | B4: 092033 | C4: =VLOOKUP(A4,'TABELA SPOLINE'!A:J,10,FALSE) -> 84.588 | D4: =C4*0.1+C4 -> 93.0468 | E4: =ROUNDUP(D4,2) -> 93.05 | F4: =E4*0.0975+E4 -> 102.12238 | G4: =ROUNDUP(F4,2) -> 102.13 | H4: 385 | I4: 2 | J4: 85-385-2 | K4: =TRIM(A4) -> 85 | L4: SPOT FLEX BCO / COBRE POL TRILHO 2 x E27 300MM | M4: 7629 | N4: Spot Line Industria E Comercio | O4: 353,45 | P4: 212,15
A5: 86 | B5: 092034 | C5: =VLOOKUP(A5,'TABELA SPOLINE'!A:J,10,FALSE) -> 101.5056 | D5: =C5*0.1+C5 -> 111.65616 | E5: =ROUNDUP(D5,2) -> 111.66 | F5: =E5*0.0975+E5 -> 122.54685 | G5: =ROUNDUP(F5,2) -> 122.55 | H5: 385 | I5: 2 | J5: 86-385-2 | K5: =TRIM(A5) -> 86 | L5: SPOT FLEX PTO / COBRE POL BASE 2 x E27 300MM | M5: 7629 | N5: Spot Line Industria E Comercio | O5: 353,45 | P5: 212,15
A6: 88 | B6: 092035 | C6: =VLOOKUP(A6,'TABELA SPOLINE'!A:J,10,FALSE) -> #N/A | H6: 385 | I6: 2 | J6: 88-385-2 | K6: =TRIM(A6) -> 88 | L6: SPOT FLEX BCO / COBRE POL BASE 2 x E27 300MM | M6: 7629 | N6: Spot Line Industria E Comercio | O6: 353,45 | P6: 212,15
A7: 90 | B7: 092036 | C7: =VLOOKUP(A7,'TABELA SPOLINE'!A:J,10,FALSE) -> 84.588 | D7: =C7*0.1+C7 -> 93.0468 | E7: =ROUNDUP(D7,2) -> 93.05 | F7: =E7*0.0975+E7 -> 102.12238 | G7: =ROUNDUP(F7,2) -> 102.13 | H7: 385 | I7: 2 | J7: 90-385-2 | K7: =TRIM(A7) -> 90 | L7: SPOT FLEX BCO TRILHO 3 x E27 500MM | M7: 7629 | N7: Spot Line Industria E Comercio | O7: 404,25 | P7: 242,65
A8: 97 | B8: 092040 | C8: =VLOOKUP(A8,'TABELA SPOLINE'!A:J,10,FALSE) -> 139.125 | D8: =C8*0.1+C8 -> 153.0375 | E8: =ROUNDUP(D8,2) -> 153.04 | F8: =E8*0.0975+E8 -> 167.9614 | G8: =ROUNDUP(F8,2) -> 167.97 | H8: 385 | I8: 3 | J8: 97-385-3 | K8: =TRIM(A8) -> 97 | L8: SPOT FLEX BCO / COBRE LIX TRILHO 3 x E27 500MM | M8: 7629 | N8: Spot Line Industria E Comercio | O8: 485,10 | P8: 291,18
A9: 98 | B9: 092041 | C9: =VLOOKUP(A9,'TABELA SPOLINE'!A:J,10,FALSE) -> 139.125 | D9: =C9*0.1+C9 -> 153.0375 | E9: =ROUNDUP(D9,2) -> 153.04 | F9: =E9*0.0975+E9 -> 167.9614 | G9: =ROUNDUP(F9,2) -> 167.97 | H9: 385 | I9: 3 | J9: 98-385-3 | K9: =TRIM(A9) -> 98 | L9: SPOT FLEX BCO / DOU POL TRILHO 3 x E27 500MM | M9: 7629 | N9: Spot Line Industria E Comercio | O9: 485,10 | P9: 291,18
A10: 99 | B10: 092042 | C10: =VLOOKUP(A10,'TABELA SPOLINE'!A:J,10,FALSE) -> 166.95 | D10: =C10*0.1+C10 -> 183.645 | E10: =ROUNDUP(D10,2) -> 183.65 | F10: =E10*0.0975+E10 -> 201.55587 | G10: =ROUNDUP(F10,2) -> 201.56 | H10: 385 | I10: 3 | J10: 99-385-3 | K10: =TRIM(A10) -> 99 | L10: SPOT FLEX PTO TRILHO 3 x E27 500MM | M10: 7629 | N10: Spot Line Industria E Comercio | O10: 404,25 | P10: 242,65
A11: 101 | B11: 092043 | C11: =VLOOKUP(A11,'TABELA SPOLINE'!A:J,10,FALSE) -> #N/A | H11: 385 | I11: 3 | J11: 101-385-3 | K11: =TRIM(A11) -> 101 | L11: SPOT FLEX PTO | M11: 7629 | N11: Spot Line Industria E Comercio | O11: 485,10 | P11: 291,18
A12: 103 | B12: 092044 | C12: =VLOOKUP(A12,'TABELA SPOLINE'!A:J,10,FALSE) -> 139.125 | D12: =C12*0.1+C12 -> 153.0375 | E12: =ROUNDUP(D12,2) -> 153.04 | F12: =E12*0.0975+E12 -> 167.9614 | G12: =ROUNDUP(F12,2) -> 167.97 | H12: 385 | I12: 3 | J12: 103-385-3 | K12: =TRIM(A12) -> 103 | L12: SPOT FLEX PTO | M12: 7629 | N12: Spot Line Industria E Comercio | O12: 485,10 | P12: 291,18
A13: 110 | B13: 092048 | C13: =VLOOKUP(A13,'TABELA SPOLINE'!A:J,10,FALSE) -> 267.12 | D13: =C13*0.1+C13 -> 293.832 | E13: =ROUNDUP(D13,2) -> 293.84 | F13: =E13*0.0975+E13 -> 322.4894 | G13: =ROUNDUP(F13,2) -> 322.49 | H13: 385 | I13: 5 | J13: 110-385-5 | K13: =TRIM(A13) -> 110 | L13: SPOT FLEX BCO | M13: 7629 | N13: Spot Line Industria E Comercio | O13: 485,10 | P13: 291,18
A14: 111 | B14: 092049 | C14: =VLOOKUP(A14,'TABELA SPOLINE'!A:J,10,FALSE) -> 267.12 | D14: =C14*0.1+C14 -> 293.832 | E14: =ROUNDUP(D14,2) -> 293.84 | F14: =E14*0.0975+E14 -> 322.4894 | G14: =ROUNDUP(F14,2) -> 322.49 | H14: 385 | I14: 5 | J14: 111-385-5 | K14: =TRIM(A14) -> 111 | L14: SPOT TROIA PTO | M14: 7629 | N14: Spot Line Industria E Comercio | O14: 353,50 | P14: 212,18
A15: 112 | B15: 092050 | C15: =VLOOKUP(A15,'TABELA SPOLINE'!A:J,10,FALSE) -> 320.544 | D15: =C15*0.1+C15 -> 352.5984 | E15: =ROUNDUP(D15,2) -> 352.6 | F15: =E15*0.0975+E15 -> 386.9785 | G15: =ROUNDUP(F15,2) -> 386.98 | H15: 385 | I15: 5 | J15: 112-385-5 | K15: =TRIM(A15) -> 112 | L15: SPOT TROIA PTO 1 x E27 120MM 120MM | M15: 7629 | N15: Spot Line Industria E Comercio | O15: 170,38 | P15: 102,27
A16: 116 | B16: 092052 | C16: =VLOOKUP(A16,'TABELA SPOLINE'!A:J,10,FALSE) -> 267.12 | D16: =C16*0.1+C16 -> 293.832 | E16: =ROUNDUP(D16,2) -> 293.84 | F16: =E16*0.0975+E16 -> 322.4894 | G16: =ROUNDUP(F16,2) -> 322.49 | H16: 385 | I16: 5 | J16: 116-385-5 | K16: =TRIM(A16) -> 116 | L16: SPOT TROIA BCO BRILHANTE | M16: 7629 | N16: Spot Line Industria E Comercio | O16: 1 056,62 | P16: 634,23
A17: 122 | B17: 092131 | C17: =VLOOKUP(A17,'TABELA SPOLINE'!A:J,10,FALSE) -> #N/A | H17: 386 | I17: 3 | J17: 122-386-3 | K17: =TRIM(A17) -> 122 | L17: SPOT TROIA PTO TRILHO 2 x E27 300MM | M17: 7629 | N17: Spot Line Industria E Comercio | O17: 747,80 | P17: 448,86
A18: 123 | B18: 092132 | C18: =VLOOKUP(A18,'TABELA SPOLINE'!A:J,10,FALSE) -> #N/A | H18: 386 | I18: 3 | J18: 123-386-3 | K18: =TRIM(A18) -> 123 | L18: SPOT TROIA PTO | M18: 7629 | N18: Spot Line Industria E Comercio | O18: 829,35 | P18: 497,81
A19: 124 | B19: 092133 | C19: =VLOOKUP(A19,'TABELA SPOLINE'!A:J,10,FALSE) -> #N/A | H19: 386 | I19: 3 | J19: 124-386-3 | K19: =TRIM(A19) -> 124 | L19: SPOT TROIA BCO | M19: 7629 | N19: Spot Line Industria E Comercio | O19: 363,82 | P19: 218,38
A20: 126 | B20: 092134 | C20: =VLOOKUP(A20,'TABELA SPOLINE'!A:J,10,FALSE) -> #N/A | H20: 386 | I20: 3 | J20: 126-386-3 | K20: =TRIM(A20) -> 126 | L20: SPOT TROIA BCO BRILHANTE | M20: 7629 | N20: Spot Line Industria E Comercio | O20: 917,75 | P20: 550,87
A21: 126 | B21: 092136 | C21: =VLOOKUP(A21,'TABELA SPOLINE'!A:J,10,FALSE) -> #N/A | H21: 386 | I21: 3 | J21: 126-386-3 | K21: =TRIM(A21) -> 126 | L21: SPOT TROIA PTO TRILHO 3 x E27 500MM | M21: 7629 | N21: Spot Line Industria E Comercio | O21: 1 408,70 | P21: 845,56
A22: 131 | B22: 092140 | C22: =VLOOKUP(A22,'TABELA SPOLINE'!A:J,10,FALSE) -> 311.64 | D22: =C22*0.1+C22 -> 342.804 | E22: =ROUNDUP(D22,2) -> 342.81 | F22: =E22*0.0975+E22 -> 376.23397 | G22: =ROUNDUP(F22,2) -> 376.24 | H22: 386 | I22: 5 | J22: 131-386-5 | K22: =TRIM(A22) -> 131 | L22: SPOT TROIA PTO | M22: 7629 | N22: Spot Line Industria E Comercio | O22: 931,02 | P22: 558,84
A23: 132 | B23: 092141 | C23: =VLOOKUP(A23,'TABELA SPOLINE'!A:J,10,FALSE) -> #N/A | H23: 386 | I23: 5 | J23: 132-386-5 | K23: =TRIM(A23) -> 132 | L23: PLAF SMART BCO 1 x E27 95MM 250MM 250MM | M23: 7629 | N23: Spot Line Industria E Comercio | O23: 232,62 | P23: 139,63
A24: 133 | B24: 092142 | C24: =VLOOKUP(A24,'TABELA SPOLINE'!A:J,10,FALSE) -> #N/A | H24: 386 | I24: 5 | J24: 133-386-5 | K24: =TRIM(A24) -> 133 | L24: PLAF SMART CAFÉ 2 x E27 95MM 250MM 250MM | M24: 7629 | N24: Spot Line Industria E Comercio | O24: 232,62 | P24: 139,63
A25: 135 | B25: 092144 | C25: =VLOOKUP(A25,'TABELA SPOLINE'!A:J,10,FALSE) -> 311.64 | D25: =C25*0.1+C25 -> 342.804 | E25: =ROUNDUP(D25,2) -> 342.81 | F25: =E25*0.0975+E25 -> 376.23397 | G25: =ROUNDUP(F25,2) -> 376.24 | H25: 386 | I25: 5 | J25: 135-386-5 | K25: =TRIM(A25) -> 135 | L25: PLAF SMART COBRE POL 2 x E27 95MM 250MM 250MM | M25: 7629 | N25: Spot Line Industria E Comercio | O25: 279,15 | P25: 167,56
A26: 154 | B26: 177939 | C26: =VLOOKUP(A26,'TABELA SPOLINE'!A:J,10,FALSE) -> #N/A | J26: 154 | K26: =TRIM(A26) -> 154 | L26: PLAF SMART DOU POL 2 x E27 95MM 250MM 250MM | M26: 7629 | N26: Spot Line Industria E Comercio | O26: 263,35 | P26: 158,07
A27: 166 | B27: 092148 | C27: =VLOOKUP(A27,'TABELA SPOLINE'!A:J,10,FALSE) -> #N/A | H27: 415 | I27: 1 | J27: 166-415-1 | K27: =TRIM(A27) -> 166 | L27: PLAF SMART PTO 2 x E27 95MM 250MM 250MM | M27: 7629 | N27: Spot Line Industria E Comercio | O27: 232,62 | P27: 139,63
A28: 167 | B28: 092149 | C28: =VLOOKUP(A28,'TABELA SPOLINE'!A:J,10,FALSE) -> #N/A | H28: 415 | I28: 1 | J28: 167-415-1 | K28: =TRIM(A28) -> 167 | L28: PLAF SMART DOU ONO 2 x E27 95MM 250MM 250MM | M28: 7629 | N28: Spot Line Industria E Comercio | O28: 232,62 | P28: 139,63
A29: 169 | B29: 092150 | C29: =VLOOKUP(A29,'TABELA SPOLINE'!A:J,10,FALSE) -> #N/A | H29: 415 | I29: 1 | J29: 169-415-1 | K29: =TRIM(A29) -> 169 | L29: PLAF SMART COBRE ONO 2 x E27 95MM 250MM 250MM | M29: 7629 | N29: Spot Line Industria E Comercio | O29: 219,45 | P29: 131,72
A30: 170 | B30: 092151 | C30: =VLOOKUP(A30,'TABELA SPOLINE'!A:J,10,FALSE) -> #N/A | H30: 415 | I30: 1 | J30: 170-415-1 | K30: =TRIM(A30) -> 170 | L30: PLAF SMART BCO 3 x E27 95MM 350MM 350MM | M30: 7629 | N30: Spot Line Industria E Comercio | O30: 382,60 | P30: 229,65
A31: 170 | B31: 178310 | C31: =VLOOKUP(A31,'TABELA SPOLINE'!A:J,10,FALSE) -> #N/A | J31: 170 | K31: =TRIM(A31) -> 170 | L31: PLAF SMART CAFÉ 3 x E27 95MM 350MM 350MM | M31: 7629 | N31: Spot Line Industria E Comercio | O31: 382,60 | P31: 229,65
A32: 171 | B32: 178309 | C32: =VLOOKUP(A32,'TABELA SPOLINE'!A:J,10,FALSE) -> #N/A | J32: 171 | K32: =TRIM(A32) -> 171 | L32: PLAF SMART COBRE POL 3 x E27 95MM 350MM 350MM | M32: 7629 | N32: Spot Line Industria E Comercio | O32: 459,12 | P32: 275,59
A33: 172 | B33: 092152 | C33: =VLOOKUP(A33,'TABELA SPOLINE'!A:J,10,FALSE) -> #N/A | H33: 415 | I33: 1 | J33: 172-415-1 | K33: =TRIM(A33) -> 172 | L33: PLAF SMART DOU POL 3 x E27 95MM 350MM 350MM | M33: 7629 | N33: Spot Line Industria E Comercio | O33: 433,12 | P33: 259,98
A34: 172 | B34: 178307 | C34: =VLOOKUP(A34,'TABELA SPOLINE'!A:J,10,FALSE) -> #N/A | J34: 172 | K34: =TRIM(A34) -> 172 | L34: PLAF SMART PTO 3 x E27 95MM 350MM 350MM | M34: 7629 | N34: Spot Line Industria E Comercio | O34: 382,60 | P34: 229,65
A35: 173 | B35: 092153 | C35: =VLOOKUP(A35,'TABELA SPOLINE'!A:J,10,FALSE) -> #N/A | H35: 415 | I35: 1 | J35: 173-415-1 | K35: =TRIM(A35) -> 173 | L35: PLAF SMART DOU ONO 3 x E27 95MM 350MM 350MM | M35: 7629 | N35: Spot Line Industria E Comercio | O35: 382,60 | P35: 229,65
A36: 174 | B36: 092154 | C36: =VLOOKUP(A36,'TABELA SPOLINE'!A:J,10,FALSE) -> #N/A | H36: 415 | I36: 1 | J36: 174-415-1 | K36: =TRIM(A36) -> 174 | L36: PLAF SMART COBRE ONO 3 x E27 95MM 350MM 350MM | M36: 7629 | N36: Spot Line Industria E Comercio | O36: 360,95 | P36: 216,66
A37: 184 | B37: 091986 | C37: =VLOOKUP(A37,'TABELA SPOLINE'!A:J,10,FALSE) -> #N/A | H37: 418 | I37: 2 | J37: 184-418-2 | K37: =TRIM(A37) -> 184 | L37: PLAF SMART BCO 5 x E27 95MM 550MM 550MM | M37: 7629 | N37: Spot Line Industria E Comercio | O37: 734,60 | P37: 440,94
A38: 185 | B38: 091987 | C38: =VLOOKUP(A38,'TABELA SPOLINE'!A:J,10,FALSE) -> #N/A | H38: 418 | I38: 2 | J38: 185-418-2 | K38: =TRIM(A38) -> 185 | L38: PLAF SMART CAFÉ 5 x E27 95MM 550MM 550MM | M38: 7629 | N38: Spot Line Industria E Comercio | O38: 734,60 | P38: 440,94
A39: 186 | B39: 091991 | C39: =VLOOKUP(A39,'TABELA SPOLINE'!A:J,10,FALSE) -> #N/A | H39: 418 | I39: 3 | J39: 186-418-3 | K39: =TRIM(A39) -> 186 | L39: PLAF SMART COBRE POL 5 x E27 95MM 550MM 550MM | M39: 7629 | N39: Spot Line Industria E Comercio | O39: 881,50 | P39: 529,11
A40: 187 | B40: 091992 | C40: =VLOOKUP(A40,'TABELA SPOLINE'!A:J,10,FALSE) -> #N/A | H40: 418 | I40: 3 | J40: 187-418-3 | K40: =TRIM(A40) -> 187 | L40: PLAF SMART DOU POL 5 x E27 95MM 550MM 550MM | M40: 7629 | N40: Spot Line Industria E Comercio | O40: 831,60 | P40: 499,16
A41: 189 | B41: 091993 | C41: =VLOOKUP(A41,'TABELA SPOLINE'!A:J,10,FALSE) -> #N/A | H41: 418 | I41: 3 | J41: 189-418-3 | K41: =TRIM(A41) -> 189 | L41: PLAF SMART PTO 5 x E27 95MM 550MM 550MM | M41: 7629 | N41: Spot Line Industria E Comercio | O41: 734,60 | P41: 440,94
A42: 192 | B42: 091994 | C42: =VLOOKUP(A42,'TABELA SPOLINE'!A:J,10,FALSE) -> #N/A | H42: 418 | I42: 3 | J42: 192-418-3 | K42: =TRIM(A42) -> 192 | L42: PLAF SMART DOU ONO 5 x E27 95MM 550MM 550MM | M42: 7629 | N42: Spot Line Industria E Comercio | O42: 734,60 | P42: 440,94
A43: 193 | B43: 091995 | C43: =VLOOKUP(A43,'TABELA SPOLINE'!A:J,10,FALSE) -> #N/A | H43: 418 | I43: 3 | J43: 193-418-3 | K43: =TRIM(A43) -> 193 | L43: PLAF SMART COBRE ONO 5 x E27 95MM 550MM 550MM | M43: 7629 | N43: Spot Line Industria E Comercio | O43: 693,00 | P43: 415,97
A44: 194 | B44: 091996 | C44: =VLOOKUP(A44,'TABELA SPOLINE'!A:J,10,FALSE) -> #N/A | H44: 418 | I44: 3 | J44: 194-418-3 | K44: =TRIM(A44) -> 194 | L44: PLAF NEW SMART BCO 3000K LED BIV 18W 1350 50MM 250MM 250MM | M44: 7629 | N44: Spot Line Industria E Comercio | O44: 361,18 | P44: 216,79
A45: 217 | B45: 092156 | C45: =VLOOKUP(A45,'TABELA SPOLINE'!A:J,10,FALSE) -> #N/A | H45: 432 | I45: 1 | J45: 217-432-1 | K45: =TRIM(A45) -> 217 | L45: PLAF NEW SMART DOU POL 3000K LED BIV 18W 1350 50MM 250MM 250MM | M45: 7629 | N45: Spot Line Industria E Comercio | O45: 408,88 | P45: 245,42
A46: 218 | B46: 092157 | C46: =VLOOKUP(A46,'TABELA SPOLINE'!A:J,10,FALSE) -> #N/A | H46: 432 | I46: 1 | J46: 218-432-1 | K46: =TRIM(A46) -> 218 | L46: PLAF NEW SMART PTO 3000K LED BIV 18W 1350 50MM 250MM 250MM | M46: 7629 | N46: Spot Line Industria E Comercio | O46: 361,18 | P46: 216,79
... A50: 228 | B50: 092163 | C50: =VLOOKUP(A50,'TABELA SPOLINE'!A:J,10,FALSE) -> #N/A | H50: 432 | I50: 4 | J50: 228-432-4 | K50: =TRIM(A50) -> 228 | L50: PLAF NEW SMART PTO 6000K LED BIV 18W 1350 50MM 250MM 250MM | M50: 7629 | N50: Spot Line Industria E Comercio | O50: 340,72 | P50: 204,52
A51: 253 | B51: 178306 | C51: =VLOOKUP(A51,'TABELA SPOLINE'!A:J,10,FALSE) -> #N/A | J51: 253 | K51: =TRIM(A51) -> 253 | L51: PLAF NEW SMART BCO 6000K LED BIV 18W 1350 50MM 250MM 250MM | M51: 7629 | N51: Spot Line Industria E Comercio | O51: 340,72 | P51: 204,52
A52: 254 | B52: 178305 | C52: =VLOOKUP(A52,'TABELA SPOLINE'!A:J,10,FALSE) -> #N/A | J52: 254 | K52: =TRIM(A52) -> 254 | L52: PLAF NEW SMART POL 6000K LED BIV 18W 1350 50MM 250MM 250MM | M52: 7629 | N52: Spot Line Industria E Comercio | O52: 389,40 | P52: 233,73
A53: 255 | B53: 178303 | C53: =VLOOKUP(A53,'TABELA SPOLINE'!A:J,10,FALSE) -> #N/A | J53: 255 | K53: =TRIM(A53) -> 255 | L53: PLAF NEW SMART BCO 3000K LED BIV 36W 2700 50MM 350MM 350MM | M53: 7629 | N53: Spot Line Industria E Comercio | O53: 471,38 | P53: 282,94
A54: 263 | B54: 092922 | C54: =VLOOKUP(A54,'TABELA SPOLINE'!A:J,10,FALSE) -> 293.832 | D54: =C54*0.1+C54 -> 323.2152 | E54: =ROUNDUP(D54,2) -> 323.22 | F54: =E54*0.0975+E54 -> 354.73395 | G54: =ROUNDUP(F54,2) -> 354.74 | H54: 449 | I54: 1 | J54: 263-449-1 | K54: =TRIM(A54) -> 263 | L54: PLAF NEW SMART COBRE POL 3000K LED BIV 36W 2700 50MM 350MM 350MM | M54: 7629 | N54: Spot Line Industria E Comercio | O54: 533,62 | P54: 320,30
A55: 265 | B55: 092923 | C55: =VLOOKUP(A55,'TABELA SPOLINE'!A:J,10,FALSE) -> 244.86 | D55: =C55*0.1+C55 -> 269.346 | E55: =ROUNDUP(D55,2) -> 269.35 | F55: =E55*0.0975+E55 -> 295.61162 | G55: =ROUNDUP(F55,2) -> 295.62 | H55: 449 | I55: 1 | J55: 265-449-1 | K55: =TRIM(A55) -> 265 | L55: PLAF NEW SMART DOU POL 3000K LED BIV 36W 2700 50MM 350MM 350MM | M55: 7629 | N55: Spot Line Industria E Comercio | O55: 533,62 | P55: 320,30
A56: 267 | B56: 092924 | C56: =VLOOKUP(A56,'TABELA SPOLINE'!A:J,10,FALSE) -> 244.86 | D56: =C56*0.1+C56 -> 269.346 | E56: =ROUNDUP(D56,2) -> 269.35 | F56: =E56*0.0975+E56 -> 295.61162 | G56: =ROUNDUP(F56,2) -> 295.62 | H56: 449 | I56: 1 | J56: 267-449-1 | K56: =TRIM(A56) -> 267 | L56: PLAF NEW SMART PTO 3000K LED BIV 36W 2700 50MM 350MM 350MM | M56: 7629 | N56: Spot Line Industria E Comercio | O56: 471,38 | P56: 282,94
A57: 277 | B57: 142218 | C57: =VLOOKUP(A57,'TABELA SPOLINE'!A:J,10,FALSE) -> #N/A | J57: 277 | K57: =TRIM(A57) -> 277 | L57: PLAF NEW SMART BCO 6000K LED BIV 36W 2700 50MM 350MM 350MM | M57: 7629 | N57: Spot Line Industria E Comercio | O57: 444,68 | P57: 266,91
A58: 277 | B58: 178311 | C58: =VLOOKUP(A58,'TABELA SPOLINE'!A:J,10,FALSE) -> #N/A | J58: 277 | K58: =TRIM(A58) -> 277 | L58: PLAF NEW SMART COBRE POL 6000K LED BIV 36W 2700 50MM 350MM 350MM | M58: 7629 | N58: Spot Line Industria E Comercio | O58: 533,62 | P58: 320,30
A59: 278 | B59: 142219 | C59: =VLOOKUP(A59,'TABELA SPOLINE'!A:J,10,FALSE) -> #N/A | J59: 278 | K59: =TRIM(A59) -> 278 | L59: PLAF NEW SMART DOU POL 6000K LED BIV 36W 2700 50MM 350MM 350MM | M59: 7629 | N59: Spot Line Industria E Comercio | O59: 533,62 | P59: 320,30
A60: 278 | B60: 178312 | C60: =VLOOKUP(A60,'TABELA SPOLINE'!A:J,10,FALSE) -> #N/A | J60: 278 | K60: =TRIM(A60) -> 278 | L60: PLAF NEW SMART POL 6000K LED BIV 36W 2700 50MM 350MM 350MM | M60: 7629 | N60: Spot Line Industria E Comercio | O60: 508,20 | P60: 305,04
A61: 279 | B61: 142220 | C61: =VLOOKUP(A61,'TABELA SPOLINE'!A:J,10,FALSE) -> #N/A | J61: 279 | K61: =TRIM(A61) -> 279 | L61: PLAF NEW SMART PTO 6000K LED BIV 36W 2700 50MM 350MM 350MM | M61: 7629 | N61: Spot Line Industria E Comercio | O61: 444,68 | P61: 266,91
A62: 279 | B62: 178313 | C62: =VLOOKUP(A62,'TABELA SPOLINE'!A:J,10,FALSE) -> #N/A | J62: 279 | K62: =TRIM(A62) -> 279 | L62: PLAF NEW SMART BCO 3000K LED BIV 50W 3750 50MM 500MM 500MM | M62: 7629 | N62: Spot Line Industria E Comercio | O62: 1 071,28 | P62: 643,02
A63: 280 | B63: 142221 | C63: =VLOOKUP(A63,'TABELA SPOLINE'!A:J,10,FALSE) -> #N/A | J63: 280 | K63: =TRIM(A63) -> 280 | L63: PLAF NEW SMART DOU POL 3000K LED BIV 50W 3750 50MM 500MM 500MM | M63: 7629 | N63: Spot Line Industria E Comercio | O63: 1 212,75 | P63: 727,94
A64: 280 | B64: 178314 | C64: =VLOOKUP(A64,'TABELA SPOLINE'!A:J,10,FALSE) -> #N/A | J64: 280 | K64: =TRIM(A64) -> 280 | L64: PLAF NEW SMART PTO 3000K LED BIV 50W 3750 50MM 500MM 500MM | M64: 7629 | N64: Spot Line Industria E Comercio | O64: 1 071,28 | P64: 643,02
A65: 281 | B65: 142222 | C65: =VLOOKUP(A65,'TABELA SPOLINE'!A:J,10,FALSE) -> #N/A | J65: 281 | K65: =TRIM(A65) -> 281 | L65: PLAF NEW SMART COBRE POL 3000K LED BIV 50W 3750 50MM 500MM 500MM | M65: 7629 | N65: Spot Line Industria E Comercio | O65: 1 212,75 | P65: 727,94
A66: 281 | B66: 178315 | C66: =VLOOKUP(A66,'TABELA SPOLINE'!A:J,10,FALSE) -> #N/A | J66: 281 | K66: =TRIM(A66) -> 281 | L66: PLAF NEW SMART POL 3000K LED BIV 50W 3750 50MM 500MM 500MM | M66: 7629 | N66: Spot Line Industria E Comercio | O66: 1 155,00 | P66: 693,28
A67: 282 | B67: 142223 | C67: =VLOOKUP(A67,'TABELA SPOLINE'!A:J,10,FALSE) -> #N/A | J67: 282 | K67: =TRIM(A67) -> 282 | L67: PLAF NEW SMART BCO 6000K LED BIV 50W 3750 50MM 500MM 500MM | M67: 7629 | N67: Spot Line Industria E Comercio | O67: 1 010,62 | P67: 606,62
A68: 282 | B68: 178316 | C68: =VLOOKUP(A68,'TABELA SPOLINE'!A:J,10,FALSE) -> #N/A | J68: 282 | K68: =TRIM(A68) -> 282 | L68: PLAF NEW SMART COBRE POL 6000K LED BIV 50W 3750 50MM 500MM 500MM | M68: 7629 | N68: Spot Line Industria E Comercio | O68: 1 212,75 | P68: 727,94
... A88: 297 | B88: 178322 | C88: =VLOOKUP(A88,'TABELA SPOLINE'!A:J,10,FALSE) -> #N/A | J88: 297 | K88: =TRIM(A88) -> 297 | L88: PLAF CASE DOU ONO 3000K LED BIV 22W 1650 80MM 300MM 300MM | M88: 7629 | N88: Spot Line Industria E Comercio | O88: 655,02 | P88: 393,17
A89: 299 | B89: 092167 | C89: =VLOOKUP(A89,'TABELA SPOLINE'!A:J,10,FALSE) -> 76.797 | D89: =C89*0.1+C89 -> 84.4767 | E89: =ROUNDUP(D89,2) -> 84.48 | F89: =E89*0.0975+E89 -> 92.7168 | G89: =ROUNDUP(F89,2) -> 92.72 | H89: 499 | I89: 1 | J89: 299-499-1 | K89: =TRIM(A89) -> 299 | L89: PLAF CASE PTO 4000K LED BIV 22W 1650 80MM 300MM 300MM | M89: 7629 | N89: Spot Line Industria E Comercio | O89: 655,02 | P89: 393,17
A90: 300 | B90: 092168 | C90: =VLOOKUP(A90,'TABELA SPOLINE'!A:J,10,FALSE) -> #N/A | H90: 499 | I90: 1 | J90: 300-499-1 | K90: =TRIM(A90) -> 300 | L90: PLAF CASE BCO FOSCO 4000K LED BIV 22W 1650 80MM 300MM 300MM | M90: 7629 | N90: Spot Line Industria E Comercio | O90: 655,02 | P90: 393,17
A91: 301 | B91: 092169 | C91: =VLOOKUP(A91,'TABELA SPOLINE'!A:J,10,FALSE) -> 92.379 | D91: =C91*0.1+C91 -> 101.6169 | E91: =ROUNDUP(D91,2) -> 101.62 | F91: =E91*0.0975+E91 -> 111.52795 | G91: =ROUNDUP(F91,2) -> 111.53 | H91: 499 | I91: 1 | J91: 301-499-1 | K91: =TRIM(A91) -> 301 | L91: PLAF CASE DOU ONO 4000K LED BIV 22W 1650 80MM 300MM 300MM | M91: 7629 | N91: Spot Line Industria E Comercio | O91: 655,02 | P91: 393,17
A92: 302 | B92: 092170 | C92: =VLOOKUP(A92,'TABELA SPOLINE'!A:J,10,FALSE) -> #N/A | H92: 499 | I92: 1 | J92: 302-499-1 | K92: =TRIM(A92) -> 302 | L92: PLAF CASE DOU ONO 3000K LED BIV 40W 3000 80MM 450MM 450MM | M92: 7629 | N92: Spot Line Industria E Comercio | O92: 1 101,88 | P92: 661,39
A93: 304 | B93: 092171 | C93: =VLOOKUP(A93,'TABELA SPOLINE'!A:J,10,FALSE) -> 76.797 | D93: =C93*0.1+C93 -> 84.4767 | E93: =ROUNDUP(D93,2) -> 84.48 | F93: =E93*0.0975+E93 -> 92.7168 | G93: =ROUNDUP(F93,2) -> 92.72 | H93: 499 | I93: 1 | J93: 304-499-1 | K93: =TRIM(A93) -> 304 | L93: PLAF CASE PTO 3000K LED BIV 40W 3000 80MM 450MM 450MM | M93: 7629 | N93: Spot Line Industria E Comercio | O93: 1 101,88 | P93: 661,39
A94: 305 | B94: 092172 | C94: =VLOOKUP(A94,'TABELA SPOLINE'!A:J,10,FALSE) -> #N/A | H94: 499 | I94: 1 | J94: 305-499-1 | K94: =TRIM(A94) -> 305 | L94: PLAF CASE BCO 3000K LED BIV 40W 3000 80MM 450MM 450MM | M94: 7629 | N94: Spot Line Industria E Comercio | O94: 1 101,88 | P94: 661,39
A95: 306 | B95: 092173 | C95: =VLOOKUP(A95,'TABELA SPOLINE'!A:J,10,FALSE) -> 92.379 | D95: =C95*0.1+C95 -> 101.6169 | E95: =ROUNDUP(D95,2) -> 101.62 | F95: =E95*0.0975+E95 -> 111.52795 | G95: =ROUNDUP(F95,2) -> 111.53 | H95: 499 | I95: 1 | J95: 306-499-1 | K95: =TRIM(A95) -> 306 | L95: PLAF CASE BCO 4000K LED BIV 40W 3000 80MM 450MM 450MM | M95: 7629 | N95: Spot Line Industria E Comercio | O95: 1 101,88 | P95: 661,39
A96: 312 | B96: 178052 | C96: =VLOOKUP(A96,'TABELA SPOLINE'!A:J,10,FALSE) -> #N/A | J96: 312 | K96: =TRIM(A96) -> 312 | L96: PLAF CASE PTO 4000K LED BIV 40W 3000 80MM 450MM 450MM | M96: 7629 | N96: Spot Line Industria E Comercio | O96: 1 101,88 | P96: 661,39
A97: 315 | B97: 178793 | C97: =VLOOKUP(A97,'TABELA SPOLINE'!A:J,10,FALSE) -> #N/A | J97: 315 | K97: =TRIM(A97) -> 315 | L97: PLAF CASE DOU ONO 4000K LED BIV 40W 3000 80MM 450MM 450MM | M97: 7629 | N97: Spot Line Industria E Comercio | O97: 1 101,88 | P97: 661,39
A98: 330 | B98: 092179 | C98: =VLOOKUP(A98,'TABELA SPOLINE'!A:J,10,FALSE) -> 150.9228 | D98: =C98*0.1+C98 -> 166.01508 | E98: =ROUNDUP(D98,2) -> 166.02 | F98: =E98*0.0975+E98 -> 182.20695 | G98: =ROUNDUP(F98,2) -> 182.21 | H98: 633 | I98: 1 | J98: 330-633-1 | K98: =TRIM(A98) -> 330 | L98: PLAF CASE PTO 3000K LED BIV 45W 3375 80MM 540MM 540MM | M98: 7629 | N98: Spot Line Industria E Comercio | O98: 1 273,28 | P98: 764,27
A99: 331 | B99: 092181 | C99: =VLOOKUP(A99,'TABELA SPOLINE'!A:J,10,FALSE) -> 125.769 | D99: =C99*0.1+C99 -> 138.3459 | E99: =ROUNDUP(D99,2) -> 138.35 | F99: =E99*0.0975+E99 -> 151.83912 | G99: =ROUNDUP(F99,2) -> 151.84 | H99: 633 | I99: 1 | J99: 331-633-1 | K99: =TRIM(A99) -> 331 | L99: PLAF CASE BCO 3000K LED BIV 45W 3375 80MM 540MM 540MM | M99: 7629 | N99: Spot Line Industria E Comercio | O99: 1 273,28 | P99: 764,27
A100: 332 | B100: 092182 | C100: =VLOOKUP(A100,'TABELA SPOLINE'!A:J,10,FALSE) -> 125.769 | D100: =C100*0.1+C100 -> 138.3459 | E100: =ROUNDUP(D100,2) -> 138.35 | F100: =E100*0.0975+E100 -> 151.83912 | G100: =ROUNDUP(F100,2) -> 151.84 | H100: 633 | I100: 1 | J100: 332-633-1 | K100: =TRIM(A100) -> 332 | L100: PLAF CASE DOU ONO 3000K LED BIV 45W 3375 80MM 540MM 540MM | M100: 7629 | N100: Spot Line Industria E Comercio | O100: 1 273,28 | P100: 764,27
A101: 338 | B101: 092186 | C101: =VLOOKUP(A101,'TABELA SPOLINE'!A:J,10,FALSE) -> 455.4396 | D101: =C101*0.1+C101 -> 500.98356 | E101: =ROUNDUP(D101,2) -> 500.99 | F101: =E101*0.0975+E101 -> 549.83653 | G101: =ROUNDUP(F101,2) -> 549.84 | H101: 633 | I101: 3 | J101: 338-633-3 | K101: =TRIM(A101) -> 338 | L101: PLAF CASE PTO 4000K LED BIV 45W 3375 80MM 540MM 540MM | M101: 7629 | N101: Spot Line Industria E Comercio | O101: 1 273,28 | P101: 764,27
A102: 339 | B102: 092187 | C102: =VLOOKUP(A102,'TABELA SPOLINE'!A:J,10,FALSE) -> 379.533 | D102: =C102*0.1+C102 -> 417.4863 | E102: =ROUNDUP(D102,2) -> 417.49 | F102: =E102*0.0975+E102 -> 458.19528 | G102: =ROUNDUP(F102,2) -> 458.2 | H102: 633 | I102: 3 | J102: 339-633-3 | K102: =TRIM(A102) -> 339 | L102: PLAF CASE BCO 4000K LED BIV 45W 3375 80MM 450MM 450MM | M102: 7629 | N102: Spot Line Industria E Comercio | O102: 1 273,28 | P102: 764,27
A103: 340 | B103: 092188 | C103: =VLOOKUP(A103,'TABELA SPOLINE'!A:J,10,FALSE) -> 379.533 | D103: =C103*0.1+C103 -> 417.4863 | E103: =ROUNDUP(D103,2) -> 417.49 | F103: =E103*0.0975+E103 -> 458.19528 | G103: =ROUNDUP(F103,2) -> 458.2 | H103: 633 | I103: 3 | J103: 340-633-3 | K103: =TRIM(A103) -> 340 | L103: PLAF CASE DOU ONO 4000K LED BIV 45W 3375 80MM 450MM 450MM | M103: 7629 | N103: Spot Line Industria E Comercio | O103: 1 273,28 | P103: 764,27
A104: 342 | B104: 092193 | C104: =VLOOKUP(A104,'TABELA SPOLINE'!A:J,10,FALSE) -> 76.797 | D104: =C104*0.1+C104 -> 84.4767 | E104: =ROUNDUP(D104,2) -> 84.48 | F104: =E104*0.0975+E104 -> 92.7168 | G104: =ROUNDUP(F104,2) -> 92.72 | H104: 634 | I104: 1 | J104: 342-634-1 | K104: =TRIM(A104) -> 342 | L104: PLAF MAZE BCO 3000K LED BIV 22W 1650 80MM 530MM 530MM | M104: 7629 | N104: Spot Line Industria E Comercio | O104: 746,82 | P104: 448,27
A105: 343 | B105: 092198 | C105: =VLOOKUP(A105,'TABELA SPOLINE'!A:J,10,FALSE) -> #N/A | H105: 634 | I105: 1 | J105: 343-634-1 | K105: =TRIM(A105) -> 343 | L105: PLAF MAZE PTO 3000K LED BIV 22W 1650 80MM 530MM 530MM | M105: 7629 | N105: Spot Line Industria E Comercio | O105: 746,82 | P105: 448,27
A106: 344 | B106: 092194 | C106: =VLOOKUP(A106,'TABELA SPOLINE'!A:J,10,FALSE) -> #N/A | H106: 634 | I106: 1 | J106: 344-634-1 | K106: =TRIM(A106) -> 344 | L106: PLAF MAZE DOU ONO 3000 K LED BIV 22W 1650 80MM 530MM 530MM | M106: 7629 | N106: Spot Line Industria E Comercio | O106: 746,82 | P106: 448,27
A107: 345 | B107: 092199 | C107: =VLOOKUP(A107,'TABELA SPOLINE'!A:J,10,FALSE) -> 92.379 | D107: =C107*0.1+C107 -> 101.6169 | E107: =ROUNDUP(D107,2) -> 101.62 | F107: =E107*0.0975+E107 -> 111.52795 | G107: =ROUNDUP(F107,2) -> 111.53 | H107: 634 | I107: 1 | J107: 345-634-1 | K107: =TRIM(A107) -> 345 | L107: PLAF MAZE BCO 4000K LED BIV 22W 1650 80MM 530MM 530MM | M107: 7629 | N107: Spot Line Industria E Comercio | O107: 746,82 | P107: 448,27
A108: 346 | B108: 092195 | C108: =VLOOKUP(A108,'TABELA SPOLINE'!A:J,10,FALSE) -> 92.379 | D108: =C108*0.1+C108 -> 101.6169 | E108: =ROUNDUP(D108,2) -> 101.62 | F108: =E108*0.0975+E108 -> 111.52795 | G108: =ROUNDUP(F108,2) -> 111.53 | H108: 634 | I108: 1 | J108: 346-634-1 | K108: =TRIM(A108) -> 346 | L108: PLAF MAZE DOU ONO 4000 K LED BIV 22W 1650 80MM 530MM 530MM | M108: 7629 | N108: Spot Line Industria E Comercio | O108: 746,82 | P108: 448,27
A109: 349 | B109: 092214 | C109: =VLOOKUP(A109,'TABELA SPOLINE'!A:J,10,FALSE) -> #N/A | J109: 349 | K109: =TRIM(A109) -> 349 | L109: PLAF MAZE PTO4000K LED BIV 22W 1650 80MM 530MM 530MM | M109: 7629 | N109: Spot Line Industria E Comercio | O109: 746,82 | P109: 448,27
A110: 349 | B110: 178244 | C110: =VLOOKUP(A110,'TABELA SPOLINE'!A:J,10,FALSE) -> #N/A | J110: 349 | K110: =TRIM(A110) -> 349 | L110: PEND SMART BCO 1 x E27 95MM 350MM 350MM 1000MM | M110: 7629 | N110: Spot Line Industria E Comercio | O110: 473,55 | P110: 284,24
A111: 350 | B111: 092215 | C111: =VLOOKUP(A111,'TABELA SPOLINE'!A:J,10,FALSE) -> #N/A | H111: 636 | I111: 1 | J111: 350-636-1 | K111: =TRIM(A111) -> 350 | L111: PEND SMART CAFÉ 1 x E27 95MM 350MM 350MM 1000MM | M111: 7629 | N111: Spot Line Industria E Comercio | O111: 473,55 | P111: 284,24
A112: 351 | B112: 092216 | C112: =VLOOKUP(A112,'TABELA SPOLINE'!A:J,10,FALSE) -> #N/A | H112: 636 | I112: 1 | J112: 351-636-1 | K112: =TRIM(A112) -> 351 | L112: PEND SMART COBRE POL 1 x E27 95MM 350MM 350MM 1000MM | M112: 7629 | N112: Spot Line Industria E Comercio | O112: 568,28 | P112: 341,10
A113: 352 | B113: 092219 | C113: =VLOOKUP(A113,'TABELA SPOLINE'!A:J,10,FALSE) -> #N/A | H113: 636 | I113: 3 | J113: 352-636-3 | K113: =TRIM(A113) -> 352 | L113: PEND SMART PTO 1 x E27 95MM 350MM 350MM 1000MM | M113: 7629 | N113: Spot Line Industria E Comercio | O113: 77,70 | P113: 46,64
A114: 353 | B114: 092220 | C114: =VLOOKUP(A114,'TABELA SPOLINE'!A:J,10,FALSE) -> #N/A | H114: 636 | I114: 3 | J114: 353-636-3 | K114: =TRIM(A114) -> 353 | L114: PEND SMART DOU POL 1 x E27 95MM 350MM 350MM 1000MM | M114: 7629 | N114: Spot Line Industria E Comercio | O114: 568,28 | P114: 341,10
A115: 355 | B115: 092221 | C115: =VLOOKUP(A115,'TABELA SPOLINE'!A:J,10,FALSE) -> #N/A | H115: 636 | I115: 3 | J115: 355-636-3 | K115: =TRIM(A115) -> 355 | L115: PEND SMART PTO 1 x E27 95MM 350MM 350MM 1000MM | M115: 7629 | N115: Spot Line Industria E Comercio | O115: 77,70 | P115: 46,64
A116: 372 | B116: 178304 | C116: =VLOOKUP(A116,'TABELA SPOLINE'!A:J,10,FALSE) -> #N/A | J116: 372 | K116: =TRIM(A116) -> 372 | L116: PEND SMART DOU ONO 1 x E27 95MM 350MM 350MM 1000MM | M116: 7629 | N116: Spot Line Industria E Comercio | O116: 473,55 | P116: 284,24
A117: 377 | B117: 178308 | C117: =VLOOKUP(A117,'TABELA SPOLINE'!A:J,10,FALSE) -> #N/A | J117: 377 | K117: =TRIM(A117) -> 377 | L117: PEND SMART COBRE ONO 1 x E27 95MM 350MM 350MM 1000MM | M117: 7629 | N117: Spot Line Industria E Comercio | O117: 473,55 | P117: 284,24
A118: 385 | B118: 179124 | C118: =VLOOKUP(A118,'TABELA SPOLINE'!A:J,10,FALSE) -> #N/A | J118: 385 | K118: =TRIM(A118) -> 385 | L118: PEND SMART BCO 1 x E27 95MM 500MM 500MM 1000MM | M118: 7629 | N118: Spot Line Industria E Comercio | O118: 857,02 | P118: 514,42
A119: 398 | B119: 092928 | C119: =VLOOKUP(A119,'TABELA SPOLINE'!A:J,10,FALSE) -> 195.888 | D119: =C119*0.1+C119 -> 215.4768 | E119: =ROUNDUP(D119,2) -> 215.48 | F119: =E119*0.0975+E119 -> 236.4893 | G119: =ROUNDUP(F119,2) -> 236.49 | H119: 646 | I119: 1 | J119: 398-646-1 | K119: =TRIM(A119) -> 398 | L119: PEND SMART CAFÉ 1 x E27 95MM 500MM 500MM 1000MM | M119: 7629 | N119: Spot Line Industria E Comercio | O119: 29,22 | P119: 17,54
A120: 399 | B120: 178183 | C120: =VLOOKUP(A120,'TABELA SPOLINE'!A:J,10,FALSE) -> #N/A | J120: 399 | K120: =TRIM(A120) -> 399 | L120: PEND SMART COBRE POL 1 x E27 95MM 500MM 500MM 1000MM | M120: 7629 | N120: Spot Line Industria E Comercio | O120: 759,55 | P120: 455,91
A121: 401 | B121: 092929 | C121: =VLOOKUP(A121,'TABELA SPOLINE'!A:J,10,FALSE) -> 235.0656 | D121: =C121*0.1+C121 -> 258.57216 | E121: =ROUNDUP(D121,2) -> 258.58 | F121: =E121*0.0975+E121 -> 283.79155 | G121: =ROUNDUP(F121,2) -> 283.8 | H121: 646 | I121: 1 | J121: 401-646-1 | K121: =TRIM(A121) -> 401 | L121: PEND SMART DOU POL 1 x E27 95MM 500MM 500MM 1000MM | M121: 7629 | N121: Spot Line Industria E Comercio | O121: 970,20 | P121: 582,35
A122: 406 | B122: 092930 | C122: =VLOOKUP(A122,'TABELA SPOLINE'!A:J,10,FALSE) -> 195.888 | D122: =C122*0.1+C122 -> 215.4768 | E122: =ROUNDUP(D122,2) -> 215.48 | F122: =E122*0.0975+E122 -> 236.4893 | G122: =ROUNDUP(F122,2) -> 236.49 | H122: 646 | I122: 1 | J122: 406-646-1 | K122: =TRIM(A122) -> 406 | L122: PEND SMART PTO 1 x E27 95MM 500MM 500MM 1000MM | M122: 7629 | N122: Spot Line Industria E Comercio | O122: 857,02 | P122: 514,42
...

Sheet Atualizados (551)
A1: SKU | B1: FORNECEDOR | C1: NOME ORIGINAL | D1: PART NUMBER | E1: CONDIÇÃO | F1: CUSTO | G1: MOEDA | H1: CUSTO FINAL? | I1: CUSTO LÍQUIDO | J1: MODIFICADO EM
A2: 092032 | B2: 7629 | E2: DDP | F2: 102.13 | G2: BRL | I2: 93.05 | J2: 45810
A3: 092033 | B3: 7629 | E3: DDP | F3: 102.13 | G3: BRL | I3: 93.05 | J3: 45810
A4: 092034 | B4: 7629 | E4: DDP | F4: 122.55 | G4: BRL | I4: 111.66 | J4: 45810
A5: 092036 | B5: 7629 | E5: DDP | F5: 102.13 | G5: BRL | I5: 93.05 | J5: 45810
A6: 092040 | B6: 7629 | E6: DDP | F6: 167.97 | G6: BRL | I6: 153.04 | J6: 45810
A7: 092041 | B7: 7629 | E7: DDP | F7: 167.97 | G7: BRL | I7: 153.04 | J7: 45810
A8: 092042 | B8: 7629 | E8: DDP | F8: 201.56 | G8: BRL | I8: 183.65 | J8: 45810
A9: 092044 | B9: 7629 | E9: DDP | F9: 167.97 | G9: BRL | I9: 153.04 | J9: 45810
A10: 092048 | B10: 7629 | E10: DDP | F10: 322.49 | G10: BRL | I10: 293.84 | J10: 45810
A11: 092049 | B11: 7629 | E11: DDP | F11: 322.49 | G11: BRL | I11: 293.84 | J11: 45810
A12: 092050 | B12: 7629 | E12: DDP | F12: 386.98 | G12: BRL | I12: 352.6 | J12: 45810
A13: 092052 | B13: 7629 | E13: DDP | F13: 322.49 | G13: BRL | I13: 293.84 | J13: 45810
... A552: 179480 | B552: 7629 | E552: DDP | F552: 278.25 | G552: BRL | I552: 253.53 | J552: 45810

Sheet Não foram atualizados (729)
A1: # Referência | B1: SKU | C1: Nome | D1: Id do Fabricante | E1: Fabricante | F1: Preço | G1: Preço Mínimo
A2: 44 | B2: 177938 | C2: SPOT FLEX PTO TRILHO 2 x E27 300MM | D2: 7629 | E2: Spot Line Industria E Comercio | F2: 519,75 | G2: 311,97
A3: 88 | B3: 092035 | C3: SPOT FLEX BCO / COBRE POL BASE 2 x E27 300MM | D3: 7629 | E3: Spot Line Industria E Comercio | F3: 353,45 | G3: 212,15
A4: 101 | B4: 092043 | C4: SPOT FLEX PTO | D4: 7629 | E4: Spot Line Industria E Comercio | F4: 485,10 | G4: 291,18
A5: 122 | B5: 092131 | C5: SPOT TROIA PTO TRILHO 2 x E27 300MM | D5: 7629 | E5: Spot Line Industria E Comercio | F5: 747,80 | G5: 448,86
A6: 123 | B6: 092132 | C6: SPOT TROIA PTO | D6: 7629 | E6: Spot Line Industria E Comercio | F6: 829,35 | G6: 497,81
A7: 124 | B7: 092133 | C7: SPOT TROIA BCO | D7: 7629 | E7: Spot Line Industria E Comercio | F7: 363,82 | G7: 218,38
A8: 126 | B8: 092134 | C8: SPOT TROIA BCO BRILHANTE | D8: 7629 | E8: Spot Line Industria E Comercio | F8: 917,75 | G8: 550,87
A9: 126 | B9: 092136 | C9: SPOT TROIA PTO TRILHO 3 x E27 500MM | D9: 7629 | E9: Spot Line Industria E Comercio | F9: 1 408,70 | G9: 845,56
A10: 132 | B10: 092141 | C10: PLAF SMART BCO 1 x E27 95MM 250MM 250MM | D10: 7629 | E10: Spot Line Industria E Comercio | F10: 232,62 | G10: 139,63
A11: 133 | B11: 092142 | C11: PLAF SMART CAFÉ 2 x E27 95MM 250MM 250MM | D11: 7629 | E11: Spot Line Industria E Comercio | F11: 232,62 | G11: 139,63
A12: 154 | B12: 177939 | C12: PLAF SMART DOU POL 2 x E27 95MM 250MM 250MM | D12: 7629 | E12: Spot Line Industria E Comercio | F12: 263,35 | G12: 158,07
A13: 166 | B13: 092148 | C13: PLAF SMART PTO 2 x E27 95MM 250MM 250MM | D13: 7629 | E13: Spot Line Industria E Comercio | F13: 232,62 | G13: 139,63
... A719: 6801 | B719: 177827 | C719: 2056 DRIVER 100 WATTS BIVOLT 23CM 48VOLTS 100W IP20 PRETO | D719: 7629 | E719: Spot Line Industria E Comercio | F719: 247,38 | G719: 148,48
B720: 177624 | C720: 1125/3 PERFIL NO FRAME TETTO BRANCO 3 METROS | D720: 7629 | E720: Spot Line Industria E Comercio | F720: 350,30 | G720: 210,26
B721: 177966 | C721: 1167/1 ARANDELA ALT C/ INTERRUPTOR PRETO 1 X MR11 391,5x 33x 439,7MM | D721: 7629 | E721: Spot Line Industria E Comercio | F721: 475,28 | G721: 285,28
B722: 179183 | C722: 1095/1 PENDENTE SET PRETO 3000 K | D722: 7629 | E722: Spot Line Industria E Comercio | F722: 303,05 | G722: 181,90
A723: 1125/3 | B723: 179393 | C723: 1219/1 PENDENTE BELL PRETO 3000K | D723: 7629 | E723: Spot Line Industria E Comercio | F723: 365,28 | G723: 219,25
A724: 1218/40 | B724: 178376 | C724: 1218/40 PENDENTE CLAIRE PRETO 3000K LED BIVOLT 12W 900LM 155,3x400x400MM | D724: 7629 | E724: Spot Line Industria E Comercio | F724: 577,72 | G724: 346,77
A725: 2012/40 | B725: 141787 | C725: 1222/31 ARANDELA CLAIRE BRANCO 3000K LED BIVOLT 5W 375LM 1053X308X443,5MM | D725: 7629 | E725: Spot Line Industria E Comercio | F725: 633,82 | G725: 380,45
A726: 499/1 | B726: 176792 | C726: 1162/15 ARANDELA LUA BRANCO 3000K LED BIVOLT 5W 375LM 47,4x150x150MM | D726: 7629 | E726: Spot Line Industria E Comercio | F726: 289,20 | G726: 173,59
A727: 778/1 | B727: 129335 | C727: CANOPLA SOBREPOR ALDODÃO 20x120x120MM | D727: 7629 | E727: Spot Line Industria E Comercio | F727: 79,58 | G727: 47,76
A728: 820/1 | B728: 129336 | C728: 1156/1 ARANDELA ARK C/ INTERRUPTOR BRANCO 3000K LED BIVOLT 2W 150LM 214,8x33x229MM | D728: 7629 | E728: Spot Line Industria E Comercio | F728: 455,38 | G728: 273,33
A729: 820/1 | B729: 129519 | C729: 1048/1 PENDENTE TORCIA BRANCO CUPULA CRU 1x E27 220x150x120x1500MM | D729: 7629 | E729: Spot Line Industria E Comercio | F729: 232,62 | G729: 139,63

Sheet Precisam ser criados (714)
A1: ID | B1: DESCRIÇÃO | C1: LAMPADA | D1: WATTS | E1: LUMENS | F1: ALTURA | G1: LARGURA | H1: COMPRIMENTO | I1: CABO | J1: PREÇO | K1: OBS.
A2: 348 | B2: 634/1 PENDENTE VERSSAT PRETO | C2: 1 X MR16 | D2: - | E2: - | F2: 500MM | G2: 50MM | H2: 50MM | I2: 1500MM | J2: 76.797
A3: 1300 | B3: 807/4 PENDENTE HONDA DOURADO POLIDO | C3: 4 X MR11 | D3: - | E3: - | F3: 130MM | G3: 50MM | H3: 1320MM | I3: 1200MM | J3: 746.6004
A4: 1304 | B4: 807/4 PENDENTE HONDA PRETO / DOURADO ESCOVADO | C4: 4 X MR11 | D4: - | E4: - | F4: 130MM | G4: 50MM | H4: 1320MM | I4: 1200MM | J4: 622.167
A5: 1314 | B5: 808/5 PENDENTE GRAU DOURADO ESCOVADO | C5: 4 X MR11 - 1 X G9 | D5: - | E5: - | F5: 140MM | G5: 120MM | H5: 1400MM | I5: 1200MM | J5: 824.0652
A6: 1315 | B6: 808/5 PENDENTE GRAU DOURADO ONO | C6: 4 X MR11 - 1 X G9 | D6: - | E6: - | F6: 140MM | G6: 120MM | H6: 1400MM | I6: 1200MM | J6: 686.721
A7: 1316 | B7: 808/5 PENDENTE GRAU DOURADO POLIDO | C7: 4 X MR11 - 1 X G9 | D7: - | E7: - | F7: 140MM | G7: 120MM | H7: 1400MM | I7: 1200MM | J7: 824.0652
A8: 1317 | B8: 808/5 PENDENTE GRAU PRETO | C8: 4 X MR11 - 1 X G9 | D8: - | E8: - | F8: 140MM | G8: 120MM | H8: 1400MM | I8: 1200MM | J8: 686.721
A9: 1318 | B9: 808/5 PENDENTE GRAU PRETO / COBRE ESCOVADO | C9: 4 X MR11 - 1 X G9 | D9: - | E9: - | F9: 140MM | G9: 120MM | H9: 1400MM | I9: 1200MM | J9: 686.721
A10: 1321 | B10: 808/5 PENDENTE GRAU PRETO / DOURADO ESCOVADO | C10: 4 X MR11 - 1 X G9 | D10: - | E10: - | F10: 140MM | G10: 120MM | H10: 1400MM | I10: 1200MM | J10: 686.721
A11: 1322 | B11: 808/5 PENDENTE GRAU PRETO / DOURADO ONO | C11: 4 X MR11 - 1 X G9 | D11: - | E11: - | F11: 140MM | G11: 120MM | H11: 1400MM | I11: 1200MM | J11: 686.721
A12: 1323 | B12: 808/5 PENDENTE GRAU PRETO / DOURADO POLIDO | C12: 4 X MR11 - 1 X G9 | D12: - | E12: - | F12: 140MM | G12: 120MM | H12: 1400MM | I12: 1200MM | J12: 686.721
A13: 1348 | B13: 812/120 PLAFON KIT PRETO3000K | C13: LED BIVOLT | D13: 38WATTS | E13: 2850 | F13: 80MM | G13: 120MM | H13: 1660MM | I13: - | J13: 363.951
A14: 1387 | B14: 817/1 ARANDELA TORCH DOURADO POLIDO CUPULA BRANCA | C14: 1 X E27 | D14: - | E14: - | F14: 500MM | G14: 90MM | H14: 140MM | I14: - | J14: 129.5532
A15: 1408 | B15: 821/1 ARANDELA MADRI BRANCO | C15: 1 X E27 | D15: - | E15: - | F15: 270MM | G15: 160MM | H15: 200MM | I15: - | J15: 150.255
A16: 1521 | B16: 837/1 COLUNA MADRI DOURADO LIXADO | C16: 1 X E27 | D16: - | E16: - | F16: 1550MM | G16: 230MM | H16: 230MM | I16: - | J16: 349.9272
A17: 1990 | B17: 647/1 COLUNA DENVER DOURADO ONO / BRANCO | C17: 1 X E27 | D17: - | E17: - | F17: 1600MM | G17: 210MM | H17: 380MM | I17: - | J17: 173.628
A18: 2151 | B18: 817/1 ARANDELA TORCH DOURADO ONO CUPULA CRU | C18: 1 X E27 | D18: - | E18: - | F18: 500MM | G18: 90MM | H18: 140MM | I18: - | J18: 110.187
A19: 2183 | B19: 817/1 ARANDELA TORCH DOURADO POLIDO CUPULA CRU | C19: 1 X E27 | D19: - | E19: - | F19: 500MM | G19: 90MM | H19: 140MM | I19: - | J19: 129.5532
A20: 2185 | B20: CUPULA TECIDO CRU 80 X 120 X 120 | C20: - | D20: - | E20: - | F20: 120MM | G20: 80MM | H20: 120MM | I20: - | J20: 26.712
A21: 2223 | B21: CUPULA TECIDO BRANCO 80 X 120 X 120 | C21: - | D21: - | E21: - | F21: 120MM | G21: 80MM | H21: 120MM | I21: - | J21: 26.712
A22: 2224 | B22: CUPULA TECIDO PRETO 80 X 120 X 120 | C22: - | D22: - | E22: - | F22: 120MM | G22: 80MM | H22: 120MM | I22: - | J22: 26.712
A23: 2571 | B23: 817/1 ARANDELA TORCH PRETA CUPULA CRU | C23: 1 X E27 | D23: - | E23: - | F23: 500MM | G23: 90MM | H23: 140MM | I23: - | J23: 110.187
A24: 2808 | B24: 817/1 ARANDELA TORCH PRETA / DOURADO ESCOVADO CUPULA CRU | C24: 1 X E27 | D24: - | E24: - | F24: 500MM | G24: 90MM | H24: 140MM | I24: - | J24: 110.187
A25: 2882 | B25: 855/1 SPOT FOCO BASE PRETO | C25: 1 X MR11 | D25: - | E25: - | F25: 110MM | G25: 100MM | H25: 100MM | I25: - | J25: 87.927
A26: 2883 | B26: 855/1 SPOT FOCO BASE DOURADO ESCOVADO | C26: 1 X MR11 | D26: - | E26: - | F26: 110MM | G26: 100MM | H26: 100MM | I26: - | J26: 104.622
A27: 4151 | B27: 896/1 ARANDELA IPE PRETO | C27: 1 X E27 | D27: - | E27: - | F27: 200MM | G27: 150MM | H27: 200MM | I27: - | J27: 107.961 | K27: C/ INTERRUPTOR
A28: 4983 | B28: 844/1 COLUNA STYLE DOURADO ONO 4000K | C28: LED BIVOLT | D28: 22 WATTS | E28: 1650 | F28: 1500MM | G28: 20MM | H28: 175MM | I28: - | J28: 228.165
A29: 5175 | B29: 855/1 SPOT FOCO BASE BRANCO | C29: 1 X MR11 | D29: - | E29: - | F29: 110MM | G29: 100MM | H29: 100MM | I29: - | J29: 87.927
A30: 5177 | B30: 887/1 ARANDELA STRING DOURADO ONO CUPULA CRU | C30: 1 X E27 | D30: - | E30: - | F30: 250MM | G30: 120MM | H30: 170MM | I30: - | J30: 171.402 | K30: C/ INTERRUPTOR
A31: 5234 | B31: 1051/30 PLAFON ELEGANCE PRETO 3000K | C31: LED BIVOLT | D31: 21 WATTS | E31: 1575 | F31: 40MM | G31: 300MM | H31: 300MM | I31: - | J31: 250.425 | K31: SOBREPOR
A32: 5235 | B32: 1051/30 PLAFON ELEGANCE BRANCO 3000K | C32: LED BIVOLT | D32: 21 WATTS | E32: 1575 | F32: 40MM | G32: 300MM | H32: 300MM | I32: - | J32: 250.425 | K32: SOBREPOR
A33: 5236 | B33: 1051/30 PLAFON ELEGANCE DOURADO ONO 3000K | C33: LED BIVOLT | D33: 21 WATTS | E33: 1575 | F33: 40MM | G33: 300MM | H33: 300MM | I33: - | J33: 250.425 | K33: SOBREPOR
A34: 5242 | B34: 1051/50 PLAFON ELEGANCE PRETO 3000K | C34: LED BIVOLT | D34: 32 WATTS | E34: 2240 | F34: 40MM | G34: 500MM | H34: 500MM | I34: - | J34: 366.177 | K34: SOBREPOR
A35: 5244 | B35: 1051/50 PLAFON ELEGANCE DOURADO ONO 3000K | C35: LED BIVOLT | D35: 32 WATTS | E35: 2240 | F35: 40MM | G35: 500MM | H35: 500MM | I35: - | J35: 366.177 | K35: SOBREPOR
A36: 5245 | B36: 1051/50 PLAFON ELEGANCE PRETO E BRANCO 3000K | C36: LED BIVOLT | D36: 32 WATTS | E36: 2240 | F36: 40MM | G36: 500MM | H36: 500MM | I36: - | J36: 366.177 | K36: SOBREPOR
A37: 5258 | B37: 1052/30 PLAFON ELEGANCE PRETO 3000K E DOIS FOCOS | C37: LED BIVOLT | D37: 21 WATTS + 4 WATTS | E37: 1875 | F37: 40MM | G37: 300MM | H37: 300MM | I37: - | J37: 321.657 | K37: SOBREPOR
A38: 5259 | B38: 1052/30 PLAFON ELEGANCE BRANCO 3000K E DOIS FOCOS | C38: LED BIVOLT | D38: 21 WATTS + 4 WATTS | E38: 1875 | F38: 40MM | G38: 300MM | H38: 300MM | I38: - | J38: 321.657 | K38: SOBREPOR
A39: 5261 | B39: 1052/30 PLAFON ELEGANCE DOURADO ONO 3000K E DOIS FOCOS | C39: LED BIVOLT | D39: 21 WATTS + 4 WATTS | E39: 1875 | F39: 40MM | G39: 300MM | H39: 300MM | I39: - | J39: 321.657 | K39: SOBREPOR
A40: 5262 | B40: 1052/30 PLAFON ELEGANCE PRETO E BRANCO 3000K E DOIS FOCOS | C40: LED BIVOLT | D40: 21 WATTS + 4 WATTS | E40: 1875 | F40: 40MM | G40: 300MM | H40: 300MM | I40: - | J40: 321.657 | K40: SOBREPOR
A41: 5267 | B41: 1052/50 PLAFON ELEGANCE PRETO 3000K E QUATRO FOCOS | C41: LED BIVOLT | D41: 32WATTS + 8 WATTS | E41: 3000 | F41: 40MM | G41: 50MM | H41: 480MM | I41: - | J41: 500.85 | K41: SOBREPOR
A42: 5268 | B42: 1052/50 PLAFON ELEGANCE BRANCO 3000K E QUATRO FOCOS | C42: LED BIVOLT | D42: 32WATTS + 8 WATTS | E42: 3000 | F42: 40MM | G42: 500MM | H42: 480MM | I42: - | J42: 500.85 | K42: SOBREPOR
... A58: 5319 | B58: 1054/48 PLAFON INFINITY DOURADO ONO 3000K E QUATRO FOCOS | C58: LED BIVOLT | D58: 34 WATTS + WATTS 8 | E58: 3150 | F58: 40MM | G58: 480MM | H58: 480MM | I58: - | J58: 584.325 | K58: SOBREPOR
A59: 5337 | B59: 1055/60 ARANDELA INFINITY PRETO 3000K COM INTERRUPTOR | C59: LED BIVOLT | D59: 20 WATTS | E59: 1500 | F59: 600MM | G59: 60MM | H59: 40MM | I59: - | J59: 184.30754
A60: 5338 | B60: 1055/60 ARANDELA INFINITY BRANCO 3000K COM INTERRUPTOR | C60: LED BIVOLT | D60: 20 WATTS | E60: 1500 | F60: 600MM | G60: 60MM | H60: 40MM | I60: - | J60: 184.30754
A61: 5339 | B61: 1055/60 ARANDELA INFINITY DOURADO ONO 3000K COM INTERRUPTOR | C61: LED BIVOLT | D61: 20 WATTS | E61: 1500 | F61: 600MM | G61: 60MM | H61: 40MM | I61: - | J61: 184.30754
A62: 5345 | B62: 1055/85 ARANDELA INFINITY PRETO 3000K COM INTERRUPTOR | C62: LED BIVOLT | D62: 30 WATTS | E62: 2250 | F62: 850MM | G62: 60MM | H62: 40MM | I62: - | J62: 221.487
A63: 5346 | B63: 1055/85 ARANDELA INFINITY BRANCO 3000K COM INTERRUPTOR | C63: LED BIVOLT | D63: 30 WATTS | E63: 2250 | F63: 850MM | G63: 60MM | H63: 40MM | I63: - | J63: 221.487
A64: 5347 | B64: 1055/85 ARANDELA INFINITY DOURADO ONO 3000K COM INTERRUPTOR | C64: LED BIVOLT | D64: 30 WATTS | E64: 2250 | F64: 850MM | G64: 60MM | H64: 40MM | I64: - | J64: 221.487
A65: 5353 | B65: 1055/120 ARANDELA INFINITY PRETO 3000K COM INTERRUPTOR | C65: LED BIVOLT | D65: 40 WATTS | E65: 3000 | F65: 1200MM | G65: 60MM | H65: 40MM | I65: - | J65: 272.685
A66: 5354 | B66: 1055/120 ARANDELA INFINITY BRANCO 3000K COM INTERRUPTOR | C66: LED BIVOLT | D66: 40 WATTS | E66: 3000 | F66: 1200MM | G66: 60MM | H66: 40MM | I66: - | J66: 272.685
A67: 5355 | B67: 1055/120 ARANDELA INFINITY DOURADO ONO 3000K COM INTERRUPTOR | C67: LED BIVOLT | D67: 40 WATTS | E67: 3000 | F67: 1200MM | G67: 60MM | H67: 40MM | I67: - | J67: 272.685
A68: 5369 | B68: 1056/60 ARANDELA INFINITY PRETO 3000K COM DOIS INTERRUPTORES E MINI SPOT | C68: LED BIVOLT | D68: 20 WATTS + 3 WATTS | E68: 1725 | F68: 600MM | G68: 60MM | H68: 40MM | I68: - | J68: 277.137
A69: 5370 | B69: 1056/60 ARANDELA INFINITY BRANCO 3000K COM DOIS INTERRUPTORES E MINI SPOT | C69: LED BIVOLT | D69: 20 WATTS + 3 WATTS | E69: 1725 | F69: 600MM | G69: 60MM | H69: 40MM | I69: - | J69: 277.137
A70: 5371 | B70: 1056/60 ARANDELA INFINITY DOURADO ONO 3000K COM DOIS INTERRUPTORES E MINI SPOT | C70: LED BIVOLT | D70: 20 WATTS + 3 WATTS | E70: 1725 | F70: 600MM | G70: 60MM | H70: 40MM | I70: - | J70: 277.137
... A108: 5453 | B108: 1060/50 EMBUTIDO CAVITY DOURADO ONO 3000K | C108: LED BIVOLT | D108: 36 WATTS | E108: 2520 | F108: 85MM | G108: 500MM | H108: 500MM | I108: - | J108: 401.74
A109: 5472 | B109: 1062/1-15 PENDENTE ZODIAC PRETO 150MM SOBREPOR | C109: 1 X MR11 | D109: - | E109: - | F109: 15MM | G109: 70MM | H109: 70MM | I109: 2000MM | J109: 122.43
A110: 5473 | B110: 1062/1-15 PENDENTE ZODIAC BRANCO 150MM SOBREPOR | C110: 1 X MR11 | D110: - | E110: - | F110: 15MM | G110: 70MM | H110: 70MM | I110: 2000MM | J110: 122.43
A111: 5474 | B111: 1062/1-15 PENDENTE ZODIAC DOURADO ONO 150MM SOBREPOR | C111: 1 X MR11 | D111: - | E111: - | F111: 15MM | G111: 70MM | H111: 70MM | I111: 2000MM | J111: 122.43
A112: 5484 | B112: 1062/5 PENDENTE ZODIAC PRETO 3X15MM E 2X250MM | C112: 5 X MR11 | D112: - | E112: - | F112: 25MM | G112: 70MM | H112: 1000MM | I112: 2000MM | J112: 533.127
A113: 5485 | B113: 1062/5 PENDENTE ZODIAC BRANCO 3X15MM E 2X250MM | C113: 5 X MR11 | D113: - | E113: - | F113: 25MM | G113: 70MM | H113: 1000MM | I113: 2000MM | J113: 533.127
A114: 5486 | B114: 1062/5 PENDENTE ZODIAC DOURADO ONO 3X15MM E 2X250MM | C114: 5 X MR11 | D114: - | E114: - | F114: 25MM | G114: 70MM | H114: 1000MM | I114: 2000MM | J114: 533.127
A115: 5516 | B115: 1067/27 PENDENTE SLICE PRETO 270MM 3000K SOBREPOR | C115: LED BIVOLT | D115: 18 WATTS | E115: 1260 | F115: 140MM | G115: 270MM | H115: 270MM | I115: 2000MM | J115: 199.227
A116: 5517 | B116: 1067/27 PENDENTE SLICE BRANCO 270MM 3000K SOBREPOR | C116: LED BIVOLT | D116: 18 WATTS | E116: 1260 | F116: 140MM | G116: 270MM | H116: 270MM | I116: 2000MM | J116: 199.227
A117: 5518 | B117: 1067/27 PENDENTE SLICE DOURADO ONO 270MM 3000K SOBREPOR | C117: LED BIVOLT | D117: 18 WATTS | E117: 1260 | F117: 140MM | G117: 270MM | H117: 270MM | I117: 2000MM | J117: 199.227
A118: 5523 | B118: 1067/27 PENDENTE SLICE DOURADO ESCOVADO 270MM 3000K SOBREPOR | C118: LED BIVOLT | D118: 18 WATTS | E118: 1260 | F118: 140MM | G118: 270MM | H118: 270MM | I118: 2000MM | J118: 221.487
A119: 5538 | B119: 1067/40 PENDENTE SLICE PRETO 400MM 3000K SOBREPOR | C119: LED BIVOLT | D119: 22 WATTS | E119: 1540 | F119: 140MM | G119: 400MM | H119: 400MM | I119: 2000MM | J119: 232.617
A120: 5539 | B120: 1067/40 PENDENTE SLICE BRANCO 400MM 3000K SOBREPOR | C120: LED BIVOLT | D120: 22 WATTS | E120: 1540 | F120: 140MM | G120: 400MM | H120: 400MM | I120: 2000MM | J120: 232.617
A121: 5540 | B121: 1067/40 PENDENTE SLICE DOURADO ONO 400MM 3000K SOBREPOR | C121: LED BIVOLT | D121: 22 WATTS | E121: 1540 | F121: 140MM | G121: 400MM | H121: 400MM | I121: 2000MM | J121: 232.617
A122: 5546 | B122: 1067/40 PENDENTE SLICE DOURADO ESCOVADO 400MM 3000K SOBREPOR | C122: LED BIVOLT | D122: 22 WATTS | E122: 1540 | F122: 140MM | G122: 400MM | H122: 400MM | I122: 2000MM | J122: 254.877
A123: 5547 | B123: 1068/18 ARANDELA SLICE PRETO 180MM 3000K | C123: LED BIVOLT | D123: 4 WATTS | E123: 280 | F123: 70MM | G123: 180MM | H123: 180MM | I123: 2000MM | J123: 110.187
A124: 5548 | B124: 1068/18 ARANDELA SLICE BRANCO 180MM 3000K | C124: LED BIVOLT | D124: 4 WATTS | E124: 280 | F124: 70MM | G124: 180MM | H124: 180MM | I124: 2000MM | J124: 110.187
A125: 5549 | B125: 1068/18 ARANDELA SLICE DOURADO ONO 180MM 3000K | C125: LED BIVOLT | D125: 4 WATTS | E125: 280 | F125: 70MM | G125: 180MM | H125: 180MM | I125: 2000MM | J125: 110.187
A126: 5555 | B126: 1068/27 PLAFON SLICE PRETO 270MM 3000K | C126: LED BIVOLT | D126: 18 WATTS | E126: 1260 | F126: 110MM | G126: 270MM | H126: 270MM | I126: 2000MM | J126: 176.967
... A131: 5565 | B131: 1068/40 PLAFON SLICE DOURADO ONO 400MM 3000K | C131: LED BIVOLT | D131: 22 WATTS | E131: 1540 | F131: 150MM | G131: 400MM | H131: 400MM | I131: 2000MM | J131: 221.487
A132: 5587 | B132: 1070/27 PENDENTE UP PRETO 270MM 3000K SOBREPOR | C132: LED BIVOLT | D132: 18 WATTS | E132: 1260 | F132: 140MM | G132: 270MM | H132: 270MM | I132: 2000MM | J132: 210.357 | K132: CANOPLA SOBREPOR
A133: 5588 | B133: 1070/27 PENDENTE UP BRANCO 270MM 3000K SOBREPOR | C133: LED BIVOLT | D133: 18 WATTS | E133: 1260 | F133: 140MM | G133: 270MM | H133: 270MM | I133: 2000MM | J133: 210.357 | K133: CANOPLA SOBREPOR
A134: 5589 | B134: 1070/27 PENDENTE UP DOURADO ONO 270MM 3000K SOBREPOR | C134: LED BIVOLT | D134: 18 WATTS | E134: 1260 | F134: 140MM | G134: 270MM | H134: 270MM | I134: 2000MM | J134: 210.357 | K134: CANOPLA SOBREPOR
A135: 5594 | B135: 1070/27 PENDENTE UP DOURADO ESCOVADO 270MM 3000K SOBREPOR | C135: LED BIVOLT | D135: 18 WATTS | E135: 1260 | F135: 140MM | G135: 270MM | H135: 270MM | I135: 2000MM | J135: 232.617 | K135: CANOPLA SOBREPOR
A136: 5595 | B136: 1070/40 PENDENTE UP PRETO 400MM 3000K SOBREPOR | C136: LED BIVOLT | D136: 22 WATTS | E136: 1540 | F136: 140MM | G136: 400MM | H136: 400MM | I136: 2000MM | J136: 239.295 | K136: CANOPLA SOBREPOR
A137: 5596 | B137: 1070/40 PENDENTE UP BRANCO 400MM 3000K SOBREPOR | C137: LED BIVOLT | D137: 22 WATTS | E137: 1540 | F137: 140MM | G137: 400MM | H137: 400MM | I137: 2000MM | J137: 239.295 | K137: CANOPLA SOBREPOR
A138: 5597 | B138: 1070/40 PENDENTE UP DOURADO ONO 400MM 3000K SOBREPOR | C138: LED BIVOLT | D138: 22 WATTS | E138: 1540 | F138: 140MM | G138: 400MM | H138: 400MM | I138: 2000MM | J138: 239.295 | K138: CANOPLA SOBREPOR
A139: 5602 | B139: 1070/40 PENDENTE UP DOURADO ESCOVADO 400MM 3000K SOBREPOR | C139: LED BIVOLT | D139: 22 WATTS | E139: 1540 | F139: 140MM | G139: 400MM | H139: 400MM | I139: 2000MM | J139: 261.555 | K139: CANOPLA SOBREPOR
A140: 5666 | B140: 1071/1000 PERFIL SOBREPOR DEL BRANCO 4 FOCOS 3000K | C140: LED BIVOLT | D140: 16WATTS + 8WATTS | E140: 1800 | F140: 55MM | G140: 40MM | H140: 1000MM | I140: - | J140: 239.295
A141: 5667 | B141: 1071/1000 PERFIL SOBREPOR DEL PRETO 4 FOCOS 3000K | C141: LED BIVOLT | D141: 16WATTS + 8WATTS | E141: 1800 | F141: 55MM | G141: 40MM | H141: 1000MM | I141: - | J141: 239.295
A142: 5669 | B142: 1071/1000 PERFIL SOBREPOR DEL BRANCO 4 FOCOS 4000K | C142: LED BIVOLT | D142: 16WATTS + 8WATTS | E142: 1800 | F142: 55MM | G142: 40MM | H142: 1000MM | I142: - | J142: 239.295
A143: 5670 | B143: 1071/1000 PERFIL SOBREPOR DEL PRETO 4 FOCOS 4000K | C143: LED BIVOLT | D143: 16WATTS + 8WATTS | E143: 1800 | F143: 55MM | G143: 40MM | H143: 1000MM | I143: - | J143: 239.295
A144: 5671 | B144: 1071/1000 PERFIL SOBREPOR DEL DOURADO ONO 4 FOCOS 4000K | C144: LED BIVOLT | D144: 16WATTS + 8WATTS | E144: 1800 | F144: 55MM | G144: 40MM | H144: 1000MM | I144: - | J144: 239.295
A145: 5672 | B145: 1071/1200 PERFIL SOBREPOR DEL BRANCO 4 FOCOS 3000K | C145: LED BIVOLT | D145: 20WATTS + 8WATTS | E145: 2100 | F145: 55MM | G145: 40MM | H145: 1200MM | I145: - | J145: 261.555
A146: 5673 | B146: 1071/1200 PERFIL SOBREPOR DEL PRETO 4 FOCOS 3000K | C146: LED BIVOLT | D146: 20WATTS + 8WATTS | E146: 2100 | F146: 55MM | G146: 40MM | H146: 1200MM | I146: - | J146: 261.555
A147: 5674 | B147: 1071/1200 PERFIL SOBREPOR DEL DOURADO ONO 4 FOCOS 3000K | C147: LED BIVOLT | D147: 20WATTS + 8WATTS | E147: 2100 | F147: 55MM | G147: 40MM | H147: 1200MM | I147: - | J147: 261.555
A148: 5675 | B148: 1071/1200 PERFIL SOBREPOR DEL BRANCO 4 FOCOS 4000K | C148: LED BIVOLT | D148: 20WATTS + 8WATTS | E148: 2100 | F148: 55MM | G148: 40MM | H148: 1200MM | I148: - | J148: 261.555
A149: 5676 | B149: 1071/1200 PERFIL SOBREPOR DEL PRETO 4 FOCOS 4000K | C149: LED BIVOLT | D149: 20WATTS + 8WATTS | E149: 2100 | F149: 55MM | G149: 40MM | H149: 1200MM | I149: - | J149: 261.555
A150: 5677 | B150: 1071/1200 PERFIL SOBREPOR DEL DOURADO ONO 4 FOCOS 4000K | C150: LED BIVOLT | D150: 20WATTS + 8WATTS | E150: 2025 | F150: 55MM | G150: 40MM | H150: 1200MM | I150: - | J150: 261.555
A151: 5678 | B151: 1071/1500 PERFIL SOBREPOR DEL BRANCO 10 FOCOS 3000K | C151: LED BIVOLT | D151: 22WATTS + 20 WATTS | E151: 3150 | F151: 55MM | G151: 40MM | H151: 1500MM | I151: - | J151: 310.527
... A162: 5695 | B162: 1072/1200 PENDENTE DEL DOURADO ONO 4 FOCOS 4000K | C162: LED BIVOLT | D162: 20WATTS + 8WATTS | E162: 2100 | F162: 55MM | G162: 40MM | H162: 1200MM | I162: 2000MM | J162: 300.51
A163: 5800 | B163: 1074/1 PENDENTE HOGAR DOURADO ONO 495MM 3000K SOBREPOR | C163: LED BIVOLT | D163: 3 WATTS | E163: 225 | F163: 500MM | G163: 25MM | H163: 35MM | I163: 2000MM | J163: 132.447 | K163: CANOPLA SOBREPOR
A164: 5801 | B164: 1074/1 PENDENTE HOGAR DOURADO POLIDO 495MM 3000K SOBREPOR | C164: LED BIVOLT | D164: 3 WATTS | E164: 225 | F164: 500MM | G164: 25MM | H164: 35MM | I164: 2000MM | J164: 158.9364 | K164: CANOPLA SOBREPOR
A165: 5802 | B165: 1074/1 PENDENTE HOGAR DOURADO ESCOVADO 495MM 3000K SOBREPOR | C165: LED BIVOLT | D165: 3 WATTS | E165: 225 | F165: 500MM | G165: 25MM | H165: 35MM | I165: 2000MM | J165: 158.9364 | K165: CANOPLA SOBREPOR
A166: 5823 | B166: 1075/1000 PERFIL EMBUTIR DEL BRANCO 4 FOCOS 3000K | C166: LED BIVOLT | D166: 16WATTS + 8WATTS | E166: 1800 | F166: 35MM | G166: 50MM | H166: 1000MM | I166: - | J166: 199.227
...
